Workbook

Sheet Leeme
A1: Cómo usar este archivo
A3: Qué es: el costeo de AndiBite con cuatro presentaciones (unidad individual, pack de 6, pack de 12 y caja de 3 sabores) y dos formas de armar el pack de 6 (opción B con bolsitas y opción C con brownies sueltos). La planta de maquila hornea y empaca; no hay planta propia.
A5: Colores:
A6: Texto azul = dato que pueden cambiar (precios, costos, mezcla, unidades por mes).
A7: Fondo amarillo = supuesto clave que todavía no está cotizado o validado.
A8: Texto negro = fórmula. Texto verde = fórmula que trae un dato de otra hoja.
A10: Hojas:
A11: Resumen: costo por presentación, resultado del año y punto de equilibrio con las opciones B y C.
A12: Supuestos: todos los datos de entrada con su fuente.
A13: Inversion: la inversión inicial, con todos los documentos y permisos para vender, y su financiamiento.
A14: Costeo: costo de producción de cada presentación, línea por línea.
A15: Proyeccion: el año 1 desglosado por canal y presentación.
... A29: Modelo v7 (10-oct-2026): app a S/2,000 (prototipo hecho), delivery agrupado, embajadoras dentro de marketing, naturista S/18.50 y quiosco S/3.20, hierro medido cada 2 meses desde julio, caja de 3 sabores en el stand a S/16.50, ferias pagadas en febrero y abril (sin Navidad), vendedor(a) pagado(a) en ferias y eventos, carné de sanidad como requisito al contratar y línea de crédito de respaldo.

Sheet Resumen
A1: AndiBite — Resumen del año 1 (enero a diciembre de 2027) y del año 2 (2028), escenario base con venta física
A2: Todo se calcula desde las hojas Supuestos, Inversion, Costeo, Proyeccion, Mensual y Anio2. Cambie las celdas azules de Supuestos, Mensual o Anio2.
A4: Presentación | B4: Costo de producción por envase | C4: Costo por unidad | D4: Precio en stand (con IGV) | E4: Margen bruto % en stand | F4: Precio por WhatsApp (con IGV) | G4: Margen bruto % por WhatsApp
A5: Unidad individual | B5: =Costeo!B15 -> 1.7204886 | C5: =Costeo!B16 -> 1.7204886 | D5: =Costeo!B19 -> 6 | E5: =Costeo!B22 -> 0.66163723 | F5: =Costeo!B25 -> 0 | G5: =Costeo!B28 -> 0
A6: Pack de 6 — opción B (con bolsitas) | B6: =Costeo!C15 -> 9.8504318 | C6: =Costeo!C16 -> 1.6417386 | D6: =Costeo!C19 -> 27.9 | E6: =Costeo!C22 -> 0.58338675 | F6: =Costeo!C25 -> 26.9 | G6: =Costeo!C28 -> 0.56789927
A7: Pack de 6 — opción C (sueltos) | B7: =Costeo!D15 -> 9.3464318 | C7: =Costeo!D16 -> 1.5577386 | D7: =Costeo!D19 -> 27.9 | E7: =Costeo!D22 -> 0.60470288 | F7: =Costeo!D25 -> 26.9 | G7: =Costeo!D28 -> 0.59000782
A8: Pack de 12 | B8: =Costeo!E15 -> 18.524864 | C8: =Costeo!E16 -> 1.5437386 | D8: =Costeo!E19 -> 51.9 | E8: =Costeo!E22 -> 0.57881813 | F8: =Costeo!E25 -> 49.9 | G8: =Costeo!E28 -> 0.56193709
A9: Caja de 3 sabores | B9: =Costeo!F15 -> 5.0249659 | C9: =Costeo!F16 -> 1.6749886 | D9: =Costeo!F19 -> 16.5 | E9: =Costeo!F22 -> 0.6406388 | F9: =Costeo!F25 -> 12 | G9: =Costeo!F28 -> 0.50587835
A11: Año 1 | B11: Opción B (bolsitas) | C11: Opción C (sueltos)
A12: Unidades vendidas | B12: =Proyeccion!F25 -> 52331 | C12: =Proyeccion!F25 -> 52331
A13: Ventas con IGV | B13: =Proyeccion!I25 -> 244728.18 | C13: =Proyeccion!I25 -> 244728.18
A14: Ventas sin IGV | B14: =Proyeccion!J25 -> 207396.76 | C14: =Proyeccion!J25 -> 207396.76
A15: Contribución (ventas sin IGV menos producción y costos variables de canal) | B15: =Proyeccion!P25 -> 97293.745 | C15: =Proyeccion!Q25 -> 98932.698
A16: Stands, carritos, ferias y eventos del año (espacio, vendedores, ferias pagadas y aportes) | B16: =SUM(Mensual!N33:N36) -> 51010 | C16: =SUM(Mensual!N33:N36) -> 51010
A17: Costos fijos del año | B17: =Supuestos!B75*12 -> 32860.667 | C17: =Supuestos!B75*12 -> 32860.667
A18: Resultado operativo del año (antes de intereses y renta anual) | B18: =B15-B16-B17 -> 13423.078 | C18: =C15-C16-C17 -> 15062.032
A19: Margen operativo sobre ventas sin IGV | B19: =IF(B14=0,0,B18/B14) -> 0.064721734 | C19: =IF(C14=0,0,C18/C14) -> 0.072624237
A20: Contribución por unidad después de stands, ferias y eventos | B20: =IF(B12=0,0,(B15-B16)/B12) -> 0.8844422 | C20: =IF(C12=0,0,(C15-C16)/C12) -> 0.91576118
A21: Punto de equilibrio (unidades al mes, promedio del año) | B21: =IF(B20<=0,"No alcanza",Supuestos!$B$75/B20) -> 3096.1762 | C21: =IF(C20<=0,"No alcanza",Supuestos!$B$75/C20) -> 2990.2871
A22: Punto de equilibrio en packs de 6 equivalentes al mes | B22: =IF(ISNUMBER(B21),B21/6,"No alcanza") -> 516.02936 | C22: =IF(ISNUMBER(C21),C21/6,"No alcanza") -> 498.38119
A23: Inversión inicial (incluye todos los documentos y permisos) | B23: =Inversion!B42 -> 40875.681 | C23: =Inversion!B42 -> 40875.681
A24: Resultado del año 1 menos la inversión (negativo = falta recuperar) | B24: =B18-B23 -> -27452.603 | C24: =C18-C23 -> -25813.649
A25: Caja más baja del año, con la cuota del préstamo (opción B) | B25: =MIN(Mensual!B44:M44) -> 2545.1418 | C25: =MIN(Mensual!B44:M44) -> 2545.1418
A26: Mes en que se recupera la inversión (mes 1 = enero de 2027; con el año 2 de la hoja Anio2) | B26: =IF(B18>=B23,"Dentro del año 1",IF(Anio2!M31>=B23,12+COUNTIF(Anio2!B31:M31,"<"&B23)+1,ROUNDUP(24+(B23-Anio2!M31)/AVERAGE(Anio2!B30:M30),0))) -> 23 | C26: —
A28: De resultado operativo a utilidad neta (año 1, opción B)
A29: Resultado operativo | B29: =B18 -> 13423.078
A30: Más: pagos a cuenta de renta ya restados en el costo de canal (1 % de las ventas sin IGV) | B30: =Supuestos!B28*B14 -> 2073.9676
A31: Menos: intereses del préstamo en el año 1 | B31: =-CUMIPMT((1+Inversion!B48)^(1/12)-1,Inversion!B49,Inversion!B47,1,12,0) -> 3965.2208
A32: Utilidad antes de impuestos | B32: =B29+B30-B31 -> 11531.825
A33: Impuesto a la renta del Régimen MYPE Tributario (10 % hasta 15 UIT de utilidad) | B33: =MAX(0,0.1*B32) -> 1153.1825
A34: Utilidad neta del año 1 | B34: =B32-B33 -> 10378.643
A35: Rentabilidad del aporte de los socios en el año 1 (utilidad neta / S/25,000) | B35: =B34/Inversion!B46 -> 0.4151457
A37: Año 2 (enero a diciembre de 2028, hoja Anio2)
A38: Unidades vendidas | B38: =Anio2!N19 -> 70452
A39: Ventas con IGV | B39: =Anio2!N22 -> 322328.8
A40: Resultado operativo del año 2 | B40: =Anio2!N30 -> 30458.668
A41: Margen operativo sobre ventas sin IGV | B41: =IF(Anio2!N23=0,0,Anio2!N30/Anio2!N23) -> 0.11150486
A42: Utilidad neta del año 2 | B42: =Anio2!B42 -> 28447.223
A43: Rentabilidad del aporte de los socios en el año 2 | B43: =Anio2!B42/Inversion!B46 -> 1.1378889
A44: Caja al cierre del año 2 (préstamo ya pagado) | B44: =Anio2!M34 -> 33683.936
A46: Notas
A47: 1. La proyección supone que los documentos (S.A.C., marca, registro sanitario, análisis, etiqueta y póliza) ya están listos al inicio de ventas (mes 1, enero de 2027). Su costo está en la hoja Inversion. El carné de sanidad es requisito al contratar.
A48: 2. La venta física (stands, carritos, ferias y eventos) es el canal principal; WhatsApp queda para la recompra, sin suscripción. Todos los puntos de venta y eventos llevan vendedor(a) pagado(a) y un(a) coordinador(a) en planilla atiende pedidos y despacho.
A49: 3. Costo de producción con sangrecita de res en polvo liofilizada (S/0.605 de insumos por brownie, polvo a S/300 por kg a granel) y maquila de S/0.45 por brownie. Cada envase trae un código único de la app Andi, Misión Hierro.
A50: 4. El resultado operativo ya incluye al personal que opera el negocio (vendedores y coordinador en planilla). La utilidad neta descuenta además los intereses del préstamo y el impuesto a la renta.
A51: 5. Respaldo: línea de crédito de S/3,000 (hoja Inversion) por si las ventas por punto bajan; con 20 % menos, la caja más baja del año 1 llegaría a unos −S/2,200 y la línea la cubre.

Sheet Supuestos
A1: Supuestos del costeo — AndiBite (maquila, escenario de 3,000 unidades al mes)
A2: Celdas azules = datos que pueden cambiar. Amarillo = supuestos clave sin cotizar. Montos en soles. Fuente general: 04-reformulacion/05-plan-comercial-y-financiero.md, sección 4.
A4: 1. Costos de producción por unidad de 20 g (sin IGV)
A5: Concepto | B5: Valor | C5: Unidad | D5: Fuente o nota
A6: Insumos por unidad (promedio de los 3 sabores, con sangrecita de res en polvo liofilizada) | B6: 0.605 | C6: S/ por unidad | D6: Receta 5 del documento 01: 22 g de sangrecita en polvo + 98 g de agua por lote de 24 (0.92 g de polvo por brownie). Polvo de res liofilizado con registro sanitario, comprado a granel en bolsas de 1 a 5 kg a S/300 por kg (en sobre de tienda cuesta S/417 a 667 por kg: Malli, Allpa Manta). Resto de insumos según documento 05 (Makro, mayoristas, Plaza Vea y Wong, sin IGV)
A7: Maquila por unidad (la planta hidrata la sangrecita en polvo, mezcla, hornea, corta, pesa y sella la bolsita) | B7: 0.45 | C7: S/ por unidad | D7: Tarifa de maquila de snacks horneados en Lima: S/20.75 por kg de producto terminado, elaboración y empaque incluidos (Organic Andean Bites, documento 03), actualizada a 2027: S/0.45 por brownie de 20 g
A8: Descuento de maquila si no se empaca cada unidad (opción C) | B8: 0 | C8: S/ por unidad | D8: [HIPÓTESIS] Dejar en 0 hasta que la planta lo confirme
A9: Bolsita individual (flow pack sin imprimir) | B9: 0.09 | C9: S/ por unidad | D9: Documento 05, tabla 4.2
A10: Etiqueta individual con rotulado completo y código único de la app (solo unidad que se vende suelta) | B10: 0.29 | C10: S/ por unidad | D10: Imprenta Peruana, 1,000 unidades sin IGV (documento 02): S/0.25, más S/0.04 por el código único impreso con dato variable (QR de la app Andi, Misión Hierro)
A11: Papel manteca separador entre brownies (opción C) | B11: 0.01 | C11: S/ por unidad | D11: [HIPÓTESIS] Rollo de supermercado prorrateado
A12: Control de calidad por lote (microbiológico y hierro medido), prorrateado por unidad | B12: =(250*12+375*9)/(12*4400) -> 0.12073864 | C12: S/ por unidad | D12: Análisis microbiológico de cada lote mensual S/250 (12 al año, documento 05) + hierro medido S/375 (el resultado se publica en la app): todos los meses de enero a junio y cada 2 meses desde julio (9 al año, cuando la receta ya es estable) / 4,400 unidades al mes en promedio del año 1
A13: Transporte planta-almacén por unidad | B13: 0.053 | C13: S/ por unidad | D13: 2 viajes de S/80 al mes / 3,000 unidades (documento 05)
A14: Almacenamiento por unidad | B14: 0.04 | C14: S/ por unidad | D14: Pactado con la planta u operador logístico (documento 05)
A15: Merma (sobre insumos, maquila y empaque) | B15: 0.05 | C15: % | D15: [HIPÓTESIS] Documento 05
A17: 2. Empaque del pack (por envase, sin IGV)
A18: Concepto | B18: Valor | C18: Unidad | D18: Fuente o nota
A19: Doypack kraft para 6 unidades | B19: 0.53 | C19: S/ por envase | D19: S/0.625 con IGV por 1,000 unidades (documento 02)
A20: Etiquetas del doypack de 6 (frente y reverso, con código único de la app) | B20: 0.76 | C20: S/ por envase | D20: 2 x S/0.36, 1,000 unidades (documento 02), más S/0.04 del código único de la app
A21: Doypack kraft para 12 unidades | B21: 0.7 | C21: S/ por envase | D21: [HIPÓTESIS] Talla mayor; cotizar
A22: Etiquetas del doypack de 12 (frente y reverso, con código único de la app) | B22: 0.76 | C22: S/ por envase | D22: Mismo sticker que el pack de 6
A23: Caja kraft para 3 sabores (lleva la etiqueta individual con el código de la app) | B23: 0.45 | C23: S/ por envase | D23: [HIPÓTESIS] Caja plegable kraft de 3 unidades, 1,000 unidades; cotizar con la imprenta del doypack
A24: 3. Impuestos y comisiones
A25: Concepto | B25: Valor | C25: Unidad | D25: Fuente o nota
A26: IGV | B26: 0.18 | C26: % | D26: SUNAT
A27: Pasarela de pagos (Yape, Plin, tarjeta) sobre el precio con IGV | B27: 0.03 | C27: % | D27: Mezcla Culqi 3.44-3.99 % con 15 % de transferencias sin costo (documento 05)
A28: Renta RMT, pago a cuenta mensual sobre la venta sin IGV | B28: 0.01 | C28: % | D28: Régimen MYPE Tributario (documento 05)
A30: 4. Costo variable de canal por unidad (sin IGV; el alquiler, el personal y las ferias van en la sección 7)
A31: Canal | B31: Logística por unidad (S/) | C31: ¿Paga pasarela? (1 = sí, 0 = no) | D31: Nota
A32: Stands y carritos (malls y supermercados) | B32: 0.27 | C32: 1 | D32: Degustación: 1 brownie regalado por cada 10 vendidos (S/0.17) + movilidad y bolsas (S/0.10) [HIPÓTESIS]
A33: Ferias y eventos | B33: 0.27 | C33: 1 | D33: Igual que el stand; el costo de la feria va aparte (sección 7)
A34: Recompra por WhatsApp e Instagram (delivery) | B34: 0.5 | C34: 1 | D34: Delivery agrupado: entregas 2 días por semana por zona (unos S/6 por pedido de 12 unidades con 3 a 4 pedidos por ruta) y recojo gratis en el stand; gratis desde 2 packs (antes S/0.80 con delivery suelto de S/9.50)
A35: Colegios (quiosco) | B35: 0.1 | C35: 0 | D35: [HIPÓTESIS] Ruta semanal al colegio; cobro por factura
A36: Tiendas naturistas | B36: 0.15 | C36: 0 | D36: [HIPÓTESIS] Reposición quincenal; cobro por factura
A38: 5. Precio que cobra AndiBite por presentación y canal (S/ con IGV)
A39: Canal | B39: Unidad individual | C39: Pack de 6 | D39: Pack de 12 | E39: Caja de 3 sabores | F39: Nota
A40: Stands y carritos (malls y supermercados) | B40: 6 | C40: 27.9 | D40: 51.9 | E40: 16.5 | F40: Precio de lista en físico. La unidad suelta (S/6.00) es la compra de prueba; la caja de 3 sabores (S/16.50, S/5.50 por brownie) es para llevar a casa; el pack de 6 (S/4.65 por brownie) es la compra conveniente. Incluye hierro medido por lote y la app Andi, Misión Hierro
A41: Ferias y eventos | B41: 6 | C41: 27.9 | D41: 51.9 | E41: 16.5 | F41: Mismo precio que en el stand
A42: Recompra por WhatsApp e Instagram (delivery) | B42: 0 | C42: 26.9 | D42: 49.9 | E42: 12 | F42: S/4.48 por brownie en el pack de 6 (Fika S/4.00 y Mamalama S/4.10 por 20 g no miden su hierro ni traen app). Por WhatsApp no se vende la unidad suelta: la caja de 3 sabores cuesta S/12.00
A43: Colegios (quiosco) | B43: 3.2 | C43: 0 | D43: 0 | E43: 0 | F43: El alumno paga S/4.00; el concesionario se queda 20 % (antes 25 %, S/3.00)
A44: Tiendas naturistas | B44: 0 | C44: 18.5 | D44: 0 | E44: 0 | F44: AndiBite cobra S/18.50 a la tienda y el anaquel queda en S/28.90: la tienda gana S/10.40 por pack (36 %; antes S/17.34, 40 %)
A46: 6. Mezcla de presentaciones por canal (% de las unidades que vende cada canal)
A47: Canal | B47: Unidad individual | C47: Pack de 6 | D47: Pack de 12 | E47: Caja de 3 sabores | F47: Suma (debe ser 100 %)
A48: Stands y carritos (malls y supermercados) | B48: 0.5 | C48: 0.35 | D48: 0.05 | E48: 0.1 | F48: =SUM(B48:E48) -> 1
A49: Ferias y eventos | B49: 0.6 | C49: 0.3 | D49: 0 | E49: 0.1 | F49: =SUM(B49:E49) -> 1
A50: Recompra por WhatsApp e Instagram (delivery) | B50: 0 | C50: 0.6 | D50: 0.3 | E50: 0.1 | F50: =SUM(B50:E50) -> 1
A51: Colegios (quiosco) | B51: 1 | C51: 0 | D51: 0 | E51: 0 | F51: =SUM(B51:E51) -> 1
A52: Tiendas naturistas | B52: 0 | C52: 1 | D52: 0 | E52: 0 | F52: =SUM(B52:E52) -> 1
A53: Stand: 5 de cada 10 brownies se venden sueltos para probar en el momento y 1 de cada 10 sale en caja de 3 sabores. WhatsApp: 60/30/10 del documento 05 (la caja de 3 reemplaza a la unidad). Resto: [HIPÓTESIS] según cómo compra cada canal.
A55: 7. Stands, carritos y ferias
A56: Concepto | B56: Valor | C56: Unidad | D56: Fuente o nota
A57: Espacio para el carrito o stand de fin de semana en mall o supermercado, por punto al mes | B57: 600 | C57: S/ al mes | D57: Módulo de 2 x 2 m en malls desde S/500 al mes (Gestión, 15-sep-2023); la entrada de un supermercado de Lima Top cuesta algo más (documento 08)
A58: Pago a vendedor(a) de stand por día | B58: 90 | C58: S/ por día | D58: Pago de impulsadoras en Lima: S/50 a 90 por día de fin de semana (Computrabajo, documento 08)
A59: Puntos de venta que atienden los socios sin pago | B59: 0 | C59: puntos | D59: Todos los puntos de venta llevan un(a) vendedor(a) pagado(a); los socios supervisan
A60: Stand en feria pagada (2 a 3 días) | B60: 1800 | C60: S/ por feria | D60: Campaña escolar (febrero) y Día del Niño Peruano (segundo domingo de abril). No hay tarifa publicada de una feria del Día del Niño; ferias parecidas de Lima: La Feria de Barranco S/1,650 a 2,000 por 2 días; Expo Eventos S/1,800 + IGV por un stand de 3 x 2 m; feria del Parque de las Leyendas S/600 por 2 x 2 m (documento 08)
A61: Días de vendedor(a) por feria pagada | B61: 3 | C61: días | D61: Una feria dura 2 a 3 días; cada día se paga a S/90 (fila 58)
A62: Brownies vendidos por feria pagada | B62: 700 | C62: unidades | D62: [HIPÓTESIS] Una mype vende unos S/3,000 por feria de PRODUCE (unos 625 brownies)
A63: Brownies por evento sin costo (kermés, cumpleaños, feria saludable o municipal) | B63: 150 | C63: unidades | D63: [HIPÓTESIS]
A64: Aporte al organizador por evento sin costo (rifa, premio o porcentaje de la venta) | B64: 70 | C64: S/ por evento | D64: Las kermeses y ferias municipales o de PRODUCE no cobran stand, pero se dona un aporte; al evento también va un(a) vendedor(a) pagado(a) 1 día (fila 58). Las ferias saludables se tratan así hasta tener su tarifa
A65: Lo vendido en físico que vuelve a comprarse por WhatsApp el mes siguiente | B65: 0.35 | C65: % de las unidades | D65: [HIPÓTESIS] Recompra con recordatorio de la app y de WhatsApp; sin suscripción
A66: Pedidos por WhatsApp del primer mes (lista de espera) | B66: 150 | C66: unidades | D66: [HIPÓTESIS]
A68: 8. Costos fijos mensuales (S/ sin IGV)
A69: Concepto | B69: S/ al mes | D69: Fuente o nota
A70: Administración: contador, software de facturación, web, teléfono, movilidad, GS1, banco, uniformes del personal de stand y app (servidor, base de datos y mantenimiento) | B70: 995 | D70: Documento 05, sección 4.1 (S/700) más S/45 al mes de uniformes y reposición del material de stand, más S/250 al mes de la app (Cloud Run y Firestore de Google, envío de recordatorios y mantenimiento de un desarrollador). El carné de sanidad ya no se paga: es requisito al contratar a vendedores y coordinador(a)
A71: Coordinador(a) comercial y de operaciones (planilla, medio tiempo de 4 horas) | B71: 709 | D71: Media remuneración mínima de 2027 (S/1,300 según el DS 015-2026-TR) más 9 % de EsSalud; microempresa en el REMYPE. Atiende WhatsApp, pedidos y despacho, y lleva el stock a los stands
A72: Marketing: pauta digital, degustaciones y material de stand (promedio del año) | B72: 700 | D72: La captación se hace en el stand; la pauta apoya las fechas clave (plan de marketing mes a mes en el documento 05)
A73: Mamás embajadoras: premio por recomendar con su código en el chat del colegio | B73: 200 | D73: Un pack de regalo o descuento por cada familia nueva que llega con su código (unas 20 al mes); premia al padre, nunca al niño (Ley 30021)
A74: Depreciación de equipos y carrito (36 meses) | B74: =Inversion!B37/36 -> 134.38889 | D74: Hoja Inversion
A75: Total costos fijos al mes | B75: =SUM(B70:B74) -> 2738.3889
A77: 9. Mezcla de sabores (para planear compras y producción)
A78: Sabor | B78: % de las unidades | D78: Nota
A79: Chispa (choco clásico con chispas) | B79: 0.4 | D79: [HIPÓTESIS] Ajustar con el focus 2
A80: Andi (choco, plátano, canela y cañihua) | B80: 0.35
A81: Lúcu (choco y lúcuma) | B81: 0.25
A82: Suma | B82: =SUM(B79:B81) -> 1

Sheet Costeo
A1: Costo de producción por presentación (sin IGV)
A2: Opción B: cada brownie en bolsita sin etiqueta, dentro del doypack con etiqueta. Opción C: brownies sueltos con papel manteca dentro del doypack. Unidad individual: bolsita con etiqueta completa. Caja de 3 sabores: 3 bolsitas en una caja kraft con una etiqueta.
A4: Concepto | B4: Unidad individual | C4: Pack de 6 — opción B (con bolsitas) | D4: Pack de 6 — opción C (sueltos) | E4: Pack de 12 (con bolsitas) | F4: Caja de 3 sabores (con bolsitas)
A5: Unidades por presentación | B5: 1 | C5: 6 | D5: 6 | E5: 12 | F5: 3
A6: Insumos | B6: =B5*Supuestos!$B$6 -> 0.605 | C6: =C5*Supuestos!$B$6 -> 3.63 | D6: =D5*Supuestos!$B$6 -> 3.63 | E6: =E5*Supuestos!$B$6 -> 7.26 | F6: =F5*Supuestos!$B$6 -> 1.815
A7: Maquila | B7: =B5*Supuestos!$B$7 -> 0.45 | C7: =C5*Supuestos!$B$7 -> 2.7 | D7: =D5*(Supuestos!$B$7-Supuestos!$B$8) -> 2.7 | E7: =E5*Supuestos!$B$7 -> 5.4 | F7: =F5*Supuestos!$B$7 -> 1.35
A8: Bolsita individual (flow pack) | B8: =B5*Supuestos!$B$9 -> 0.09 | C8: =C5*Supuestos!$B$9 -> 0.54 | D8: 0 | E8: =E5*Supuestos!$B$9 -> 1.08 | F8: =F5*Supuestos!$B$9 -> 0.27
A9: Etiqueta individual (con código de la app) | B9: =Supuestos!$B$10 -> 0.29 | C9: 0 | D9: 0 | E9: 0 | F9: =Supuestos!$B$10 -> 0.29
A10: Papel manteca separador | B10: 0 | C10: 0 | D10: =D5*Supuestos!$B$11 -> 0.06 | E10: 0 | F10: 0
A11: Doypack o caja | B11: 0 | C11: =Supuestos!$B$19 -> 0.53 | D11: =Supuestos!$B$19 -> 0.53 | E11: =Supuestos!$B$21 -> 0.7 | F11: =Supuestos!$B$23 -> 0.45
A12: Etiquetas del doypack | B12: 0 | C12: =Supuestos!$B$20 -> 0.76 | D12: =Supuestos!$B$20 -> 0.76 | E12: =Supuestos!$B$22 -> 0.76 | F12: 0
A13: Merma | B13: =Supuestos!$B$15*SUM(B6:B12) -> 0.07175 | C13: =Supuestos!$B$15*SUM(C6:C12) -> 0.408 | D13: =Supuestos!$B$15*SUM(D6:D12) -> 0.384 | E13: =Supuestos!$B$15*SUM(E6:E12) -> 0.76 | F13: =Supuestos!$B$15*SUM(F6:F12) -> 0.20875
A14: Control de calidad, transporte y almacén | B14: =B5*(Supuestos!$B$12+Supuestos!$B$13+Supuestos!$B$14) -> 0.21373864 | C14: =C5*(Supuestos!$B$12+Supuestos!$B$13+Supuestos!$B$14) -> 1.2824318 | D14: =D5*(Supuestos!$B$12+Supuestos!$B$13+Supuestos!$B$14) -> 1.2824318 | E14: =E5*(Supuestos!$B$12+Supuestos!$B$13+Supuestos!$B$14) -> 2.5648636 | F14: =F5*(Supuestos!$B$12+Supuestos!$B$13+Supuestos!$B$14) -> 0.64121591
A15: Costo de producción por presentación | B15: =SUM(B6:B14) -> 1.7204886 | C15: =SUM(C6:C14) -> 9.8504318 | D15: =SUM(D6:D14) -> 9.3464318 | E15: =SUM(E6:E14) -> 18.524864 | F15: =SUM(F6:F14) -> 5.0249659
A16: Costo de producción por unidad | B16: =IF(B5=0,0,B15/B5) -> 1.7204886 | C16: =IF(C5=0,0,C15/C5) -> 1.6417386 | D16: =IF(D5=0,0,D15/D5) -> 1.5577386 | E16: =IF(E5=0,0,E15/E5) -> 1.5437386 | F16: =IF(F5=0,0,F15/F5) -> 1.6749886
A18: Venta en stand o carrito (precio de lista en físico)
A19: Precio con IGV | B19: =Supuestos!B40 -> 6 | C19: =Supuestos!C40 -> 27.9 | D19: =Supuestos!C40 -> 27.9 | E19: =Supuestos!D40 -> 51.9 | F19: =Supuestos!E40 -> 16.5
A20: Precio sin IGV | B20: =B19/(1+Supuestos!$B$26) -> 5.0847458 | C20: =C19/(1+Supuestos!$B$26) -> 23.644068 | D20: =D19/(1+Supuestos!$B$26) -> 23.644068 | E20: =E19/(1+Supuestos!$B$26) -> 43.983051 | F20: =F19/(1+Supuestos!$B$26) -> 13.983051
A21: Margen bruto por presentación (precio sin IGV menos costo de producción) | B21: =B20-B15 -> 3.3642571 | C21: =C20-C15 -> 13.793636 | D21: =D20-D15 -> 14.297636 | E21: =E20-E15 -> 25.458187 | F21: =F20-F15 -> 8.9580849
A22: Margen bruto % | B22: =IF(B20=0,0,B21/B20) -> 0.66163723 | C22: =IF(C20=0,0,C21/C20) -> 0.58338675 | D22: =IF(D20=0,0,D21/D20) -> 0.60470288 | E22: =IF(E20=0,0,E21/E20) -> 0.57881813 | F22: =IF(F20=0,0,F21/F20) -> 0.6406388
A24: Recompra por WhatsApp e Instagram
A25: Precio con IGV | B25: =Supuestos!B42 -> 0 | C25: =Supuestos!C42 -> 26.9 | D25: =Supuestos!C42 -> 26.9 | E25: =Supuestos!D42 -> 49.9 | F25: =Supuestos!E42 -> 12
A26: Precio sin IGV | B26: =B25/(1+Supuestos!$B$26) -> 0 | C26: =C25/(1+Supuestos!$B$26) -> 22.79661 | D26: =D25/(1+Supuestos!$B$26) -> 22.79661 | E26: =E25/(1+Supuestos!$B$26) -> 42.288136 | F26: =F25/(1+Supuestos!$B$26) -> 10.169492
A27: Margen bruto por presentación (precio sin IGV menos costo de producción) | B27: =B26-B15 -> -1.7204886 | C27: =C26-C15 -> 12.946178 | D27: =D26-D15 -> 13.450178 | E27: =E26-E15 -> 23.763272 | F27: =F26-F15 -> 5.1445256
A28: Margen bruto % | B28: =IF(B26=0,0,B27/B26) -> 0 | C28: =IF(C26=0,0,C27/C26) -> 0.56789927 | D28: =IF(D26=0,0,D27/D26) -> 0.59000782 | E28: =IF(E26=0,0,E27/E26) -> 0.56193709 | F28: =IF(F26=0,0,F27/F26) -> 0.50587835
A30: El margen bruto no incluye alquiler del stand, personal, delivery, pasarela, comisiones ni costos fijos: eso se calcula en las hojas Proyeccion y Mensual.

Sheet Proyeccion
A1: Proyección anual por canal y presentación (año 1: enero a diciembre de 2027)
A2: Paso a paso: unidades del canal (hoja Mensual) × mezcla de presentaciones (Supuestos) = unidades por presentación; ÷ tamaño = envases vendidos; × precio = ingreso; menos costo de producción y costo variable de canal = contribución.
A4: Canal | B4: Presentación | C4: Unidades por envase | D4: Unidades del canal en el año | E4: % de la mezcla | F4: Unidades vendidas | G4: Envases vendidos | H4: Precio cobrado con IGV por envase | I4: Ingreso con IGV | J4: Ingreso sin IGV | K4: Costo de producción por envase — opción B | L4: Costo de producción por envase — opción C | M4: Costo variable de canal por envase | N4: Contribución por envase — opción B | O4: Contribución por envase — opción C | P4: Contribución total — opción B | Q4: Contribución total — opción C | R4: Margen de contribución % — B | S4: Margen de contribución % — C
A5: Stands y carritos (malls y supermercados) | B5: Unidad individual | C5: =Costeo!B5 -> 1 | D5: =Mensual!$N$14 -> 22625 | E5: =Supuestos!B48 -> 0.5 | F5: =D5*E5 -> 11312.5 | G5: =IF(C5=0,0,F5/C5) -> 11312.5 | H5: =Supuestos!B40 -> 6 | I5: =G5*H5 -> 67875 | J5: =I5/(1+Supuestos!$B$26) -> 57521.186 | K5: =Costeo!B15 -> 1.7204886 | L5: =Costeo!B15 -> 1.7204886 | M5: =IF(H5=0,0,C5*Supuestos!$B$32+H5*Supuestos!$B$27*Supuestos!$C$32+H5/(1+Supuestos!$B$26)*Supuestos!$B$28) -> 0.50084746 | N5: =IF(H5=0,0,H5/(1+Supuestos!$B$26)-K5-M5) -> 2.8634097 | O5: =IF(H5=0,0,H5/(1+Supuestos!$B$26)-L5-M5) -> 2.8634097 | P5: =G5*N5 -> 32392.322 | Q5: =G5*O5 -> 32392.322 | R5: =IF(H5=0,0,N5/(H5/(1+Supuestos!$B$26))) -> 0.56313723 | S5: =IF(H5=0,0,O5/(H5/(1+Supuestos!$B$26))) -> 0.56313723
A6: Stands y carritos (malls y supermercados) | B6: Pack de 6 | C6: =Costeo!C5 -> 6 | D6: =Mensual!$N$14 -> 22625 | E6: =Supuestos!C48 -> 0.35 | F6: =D6*E6 -> 7918.75 | G6: =IF(C6=0,0,F6/C6) -> 1319.7917 | H6: =Supuestos!C40 -> 27.9 | I6: =G6*H6 -> 36822.188 | J6: =I6/(1+Supuestos!$B$26) -> 31205.244 | K6: =Costeo!C15 -> 9.8504318 | L6: =Costeo!D15 -> 9.3464318 | M6: =IF(H6=0,0,C6*Supuestos!$B$32+H6*Supuestos!$B$27*Supuestos!$C$32+H6/(1+Supuestos!$B$26)*Supuestos!$B$28) -> 2.6934407 | N6: =IF(H6=0,0,H6/(1+Supuestos!$B$26)-K6-M6) -> 11.100195 | O6: =IF(H6=0,0,H6/(1+Supuestos!$B$26)-L6-M6) -> 11.604195 | P6: =G6*N6 -> 14649.945 | Q6: =G6*O6 -> 15315.12 | R6: =IF(H6=0,0,N6/(H6/(1+Supuestos!$B$26))) -> 0.46947063 | S6: =IF(H6=0,0,O6/(H6/(1+Supuestos!$B$26))) -> 0.49078675
A7: Stands y carritos (malls y supermercados) | B7: Pack de 12 | C7: =Costeo!E5 -> 12 | D7: =Mensual!$N$14 -> 22625 | E7: =Supuestos!D48 -> 0.05 | F7: =D7*E7 -> 1131.25 | G7: =IF(C7=0,0,F7/C7) -> 94.270833 | H7: =Supuestos!D40 -> 51.9 | I7: =G7*H7 -> 4892.6562 | J7: =I7/(1+Supuestos!$B$26) -> 4146.3189 | K7: =Costeo!E15 -> 18.524864 | L7: =Costeo!E15 -> 18.524864 | M7: =IF(H7=0,0,C7*Supuestos!$B$32+H7*Supuestos!$B$27*Supuestos!$C$32+H7/(1+Supuestos!$B$26)*Supuestos!$B$28) -> 5.2368305 | N7: =IF(H7=0,0,H7/(1+Supuestos!$B$26)-K7-M7) -> 20.221357 | O7: =IF(H7=0,0,H7/(1+Supuestos!$B$26)-L7-M7) -> 20.221357 | P7: =G7*N7 -> 1906.2841 | Q7: =G7*O7 -> 1906.2841 | R7: =IF(H7=0,0,N7/(H7/(1+Supuestos!$B$26))) -> 0.45975339 | S7: =IF(H7=0,0,O7/(H7/(1+Supuestos!$B$26))) -> 0.45975339
A8: Stands y carritos (malls y supermercados) | B8: Caja de 3 sabores | C8: =Costeo!F5 -> 3 | D8: =Mensual!$N$14 -> 22625 | E8: =Supuestos!E48 -> 0.1 | F8: =D8*E8 -> 2262.5 | G8: =IF(C8=0,0,F8/C8) -> 754.16667 | H8: =Supuestos!E40 -> 16.5 | I8: =G8*H8 -> 12443.75 | J8: =I8/(1+Supuestos!$B$26) -> 10545.551 | K8: =Costeo!F15 -> 5.0249659 | L8: =Costeo!F15 -> 5.0249659 | M8: =IF(H8=0,0,C8*Supuestos!$B$32+H8*Supuestos!$B$27*Supuestos!$C$32+H8/(1+Supuestos!$B$26)*Supuestos!$B$28) -> 1.4448305 | N8: =IF(H8=0,0,H8/(1+Supuestos!$B$26)-K8-M8) -> 7.5132544 | O8: =IF(H8=0,0,H8/(1+Supuestos!$B$26)-L8-M8) -> 7.5132544 | P8: =G8*N8 -> 5666.246 | Q8: =G8*O8 -> 5666.246 | R8: =IF(H8=0,0,N8/(H8/(1+Supuestos!$B$26))) -> 0.53731153 | S8: =IF(H8=0,0,O8/(H8/(1+Supuestos!$B$26))) -> 0.53731153
A9: Ferias y eventos | B9: Unidad individual | C9: =Costeo!B5 -> 1 | D9: =Mensual!$N$15 -> 7400 | E9: =Supuestos!B49 -> 0.6 | F9: =D9*E9 -> 4440 | G9: =IF(C9=0,0,F9/C9) -> 4440 | H9: =Supuestos!B41 -> 6 | I9: =G9*H9 -> 26640 | J9: =I9/(1+Supuestos!$B$26) -> 22576.271 | K9: =Costeo!B15 -> 1.7204886 | L9: =Costeo!B15 -> 1.7204886 | M9: =IF(H9=0,0,C9*Supuestos!$B$33+H9*Supuestos!$B$27*Supuestos!$C$33+H9/(1+Supuestos!$B$26)*Supuestos!$B$28) -> 0.50084746 | N9: =IF(H9=0,0,H9/(1+Supuestos!$B$26)-K9-M9) -> 2.8634097 | O9: =IF(H9=0,0,H9/(1+Supuestos!$B$26)-L9-M9) -> 2.8634097 | P9: =G9*N9 -> 12713.539 | Q9: =G9*O9 -> 12713.539 | R9: =IF(H9=0,0,N9/(H9/(1+Supuestos!$B$26))) -> 0.56313723 | S9: =IF(H9=0,0,O9/(H9/(1+Supuestos!$B$26))) -> 0.56313723
A10: Ferias y eventos | B10: Pack de 6 | C10: =Costeo!C5 -> 6 | D10: =Mensual!$N$15 -> 7400 | E10: =Supuestos!C49 -> 0.3 | F10: =D10*E10 -> 2220 | G10: =IF(C10=0,0,F10/C10) -> 370 | H10: =Supuestos!C41 -> 27.9 | I10: =G10*H10 -> 10323 | J10: =I10/(1+Supuestos!$B$26) -> 8748.3051 | K10: =Costeo!C15 -> 9.8504318 | L10: =Costeo!D15 -> 9.3464318 | M10: =IF(H10=0,0,C10*Supuestos!$B$33+H10*Supuestos!$B$27*Supuestos!$C$33+H10/(1+Supuestos!$B$26)*Supuestos!$B$28) -> 2.6934407 | N10: =IF(H10=0,0,H10/(1+Supuestos!$B$26)-K10-M10) -> 11.100195 | O10: =IF(H10=0,0,H10/(1+Supuestos!$B$26)-L10-M10) -> 11.604195 | P10: =G10*N10 -> 4107.0723 | Q10: =G10*O10 -> 4293.5523 | R10: =IF(H10=0,0,N10/(H10/(1+Supuestos!$B$26))) -> 0.46947063 | S10: =IF(H10=0,0,O10/(H10/(1+Supuestos!$B$26))) -> 0.49078675
A11: Ferias y eventos | B11: Pack de 12 | C11: =Costeo!E5 -> 12 | D11: =Mensual!$N$15 -> 7400 | E11: =Supuestos!D49 -> 0 | F11: =D11*E11 -> 0 | G11: =IF(C11=0,0,F11/C11) -> 0 | H11: =Supuestos!D41 -> 51.9 | I11: =G11*H11 -> 0 | J11: =I11/(1+Supuestos!$B$26) -> 0 | K11: =Costeo!E15 -> 18.524864 | L11: =Costeo!E15 -> 18.524864 | M11: =IF(H11=0,0,C11*Supuestos!$B$33+H11*Supuestos!$B$27*Supuestos!$C$33+H11/(1+Supuestos!$B$26)*Supuestos!$B$28) -> 5.2368305 | N11: =IF(H11=0,0,H11/(1+Supuestos!$B$26)-K11-M11) -> 20.221357 | O11: =IF(H11=0,0,H11/(1+Supuestos!$B$26)-L11-M11) -> 20.221357 | P11: =G11*N11 -> 0 | Q11: =G11*O11 -> 0 | R11: =IF(H11=0,0,N11/(H11/(1+Supuestos!$B$26))) -> 0.45975339 | S11: =IF(H11=0,0,O11/(H11/(1+Supuestos!$B$26))) -> 0.45975339
A12: Ferias y eventos | B12: Caja de 3 sabores | C12: =Costeo!F5 -> 3 | D12: =Mensual!$N$15 -> 7400 | E12: =Supuestos!E49 -> 0.1 | F12: =D12*E12 -> 740 | G12: =IF(C12=0,0,F12/C12) -> 246.66667 | H12: =Supuestos!E41 -> 16.5 | I12: =G12*H12 -> 4070 | J12: =I12/(1+Supuestos!$B$26) -> 3449.1525 | K12: =Costeo!F15 -> 5.0249659 | L12: =Costeo!F15 -> 5.0249659 | M12: =IF(H12=0,0,C12*Supuestos!$B$33+H12*Supuestos!$B$27*Supuestos!$C$33+H12/(1+Supuestos!$B$26)*Supuestos!$B$28) -> 1.4448305 | N12: =IF(H12=0,0,H12/(1+Supuestos!$B$26)-K12-M12) -> 7.5132544 | O12: =IF(H12=0,0,H12/(1+Supuestos!$B$26)-L12-M12) -> 7.5132544 | P12: =G12*N12 -> 1853.2694 | Q12: =G12*O12 -> 1853.2694 | R12: =IF(H12=0,0,N12/(H12/(1+Supuestos!$B$26))) -> 0.53731153 | S12: =IF(H12=0,0,O12/(H12/(1+Supuestos!$B$26))) -> 0.53731153
A13: Recompra por WhatsApp e Instagram (delivery) | B13: Unidad individual | C13: =Costeo!B5 -> 1 | D13: =Mensual!$N$16 -> 9421 | E13: =Supuestos!B50 -> 0 | F13: =D13*E13 -> 0 | G13: =IF(C13=0,0,F13/C13) -> 0 | H13: =Supuestos!B42 -> 0 | I13: =G13*H13 -> 0 | J13: =I13/(1+Supuestos!$B$26) -> 0 | K13: =Costeo!B15 -> 1.7204886 | L13: =Costeo!B15 -> 1.7204886 | M13: =IF(H13=0,0,C13*Supuestos!$B$34+H13*Supuestos!$B$27*Supuestos!$C$34+H13/(1+Supuestos!$B$26)*Supuestos!$B$28) -> 0 | N13: =IF(H13=0,0,H13/(1+Supuestos!$B$26)-K13-M13) -> 0 | O13: =IF(H13=0,0,H13/(1+Supuestos!$B$26)-L13-M13) -> 0 | P13: =G13*N13 -> 0 | Q13: =G13*O13 -> 0 | R13: =IF(H13=0,0,N13/(H13/(1+Supuestos!$B$26))) -> 0 | S13: =IF(H13=0,0,O13/(H13/(1+Supuestos!$B$26))) -> 0
A14: Recompra por WhatsApp e Instagram (delivery) | B14: Pack de 6 | C14: =Costeo!C5 -> 6 | D14: =Mensual!$N$16 -> 9421 | E14: =Supuestos!C50 -> 0.6 | F14: =D14*E14 -> 5652.6 | G14: =IF(C14=0,0,F14/C14) -> 942.1 | H14: =Supuestos!C42 -> 26.9 | I14: =G14*H14 -> 25342.49 | J14: =I14/(1+Supuestos!$B$26) -> 21476.686 | K14: =Costeo!C15 -> 9.8504318 | L14: =Costeo!D15 -> 9.3464318 | M14: =IF(H14=0,0,C14*Supuestos!$B$34+H14*Supuestos!$B$27*Supuestos!$C$34+H14/(1+Supuestos!$B$26)*Supuestos!$B$28) -> 4.0349661 | N14: =IF(H14=0,0,H14/(1+Supuestos!$B$26)-K14-M14) -> 8.9112122 | O14: =IF(H14=0,0,H14/(1+Supuestos!$B$26)-L14-M14) -> 9.4152122 | P14: =G14*N14 -> 8395.2531 | Q14: =G14*O14 -> 8870.0715 | R14: =IF(H14=0,0,N14/(H14/(1+Supuestos!$B$26))) -> 0.39090076 | S14: =IF(H14=0,0,O14/(H14/(1+Supuestos!$B$26))) -> 0.41300931
A15: Recompra por WhatsApp e Instagram (delivery) | B15: Pack de 12 | C15: =Costeo!E5 -> 12 | D15: =Mensual!$N$16 -> 9421 | E15: =Supuestos!D50 -> 0.3 | F15: =D15*E15 -> 2826.3 | G15: =IF(C15=0,0,F15/C15) -> 235.525 | H15: =Supuestos!D42 -> 49.9 | I15: =G15*H15 -> 11752.698 | J15: =I15/(1+Supuestos!$B$26) -> 9959.9131 | K15: =Costeo!E15 -> 18.524864 | L15: =Costeo!E15 -> 18.524864 | M15: =IF(H15=0,0,C15*Supuestos!$B$34+H15*Supuestos!$B$27*Supuestos!$C$34+H15/(1+Supuestos!$B$26)*Supuestos!$B$28) -> 7.9198814 | N15: =IF(H15=0,0,H15/(1+Supuestos!$B$26)-K15-M15) -> 15.843391 | O15: =IF(H15=0,0,H15/(1+Supuestos!$B$26)-L15-M15) -> 15.843391 | P15: =G15*N15 -> 3731.5146 | Q15: =G15*O15 -> 3731.5146 | R15: =IF(H15=0,0,N15/(H15/(1+Supuestos!$B$26))) -> 0.37465332 | S15: =IF(H15=0,0,O15/(H15/(1+Supuestos!$B$26))) -> 0.37465332
A16: Recompra por WhatsApp e Instagram (delivery) | B16: Caja de 3 sabores | C16: =Costeo!F5 -> 3 | D16: =Mensual!$N$16 -> 9421 | E16: =Supuestos!E50 -> 0.1 | F16: =D16*E16 -> 942.1 | G16: =IF(C16=0,0,F16/C16) -> 314.03333 | H16: =Supuestos!E42 -> 12 | I16: =G16*H16 -> 3768.4 | J16: =I16/(1+Supuestos!$B$26) -> 3193.5593 | K16: =Costeo!F15 -> 5.0249659 | L16: =Costeo!F15 -> 5.0249659 | M16: =IF(H16=0,0,C16*Supuestos!$B$34+H16*Supuestos!$B$27*Supuestos!$C$34+H16/(1+Supuestos!$B$26)*Supuestos!$B$28) -> 1.9616949 | N16: =IF(H16=0,0,H16/(1+Supuestos!$B$26)-K16-M16) -> 3.1828307 | O16: =IF(H16=0,0,H16/(1+Supuestos!$B$26)-L16-M16) -> 3.1828307 | P16: =G16*N16 -> 999.51493 | Q16: =G16*O16 -> 999.51493 | R16: =IF(H16=0,0,N16/(H16/(1+Supuestos!$B$26))) -> 0.31297835 | S16: =IF(H16=0,0,O16/(H16/(1+Supuestos!$B$26))) -> 0.31297835
A17: Colegios (quiosco) | B17: Unidad individual | C17: =Costeo!B5 -> 1 | D17: =Mensual!$N$17 -> 9165 | E17: =Supuestos!B51 -> 1 | F17: =D17*E17 -> 9165 | G17: =IF(C17=0,0,F17/C17) -> 9165 | H17: =Supuestos!B43 -> 3.2 | I17: =G17*H17 -> 29328 | J17: =I17/(1+Supuestos!$B$26) -> 24854.237 | K17: =Costeo!B15 -> 1.7204886 | L17: =Costeo!B15 -> 1.7204886 | M17: =IF(H17=0,0,C17*Supuestos!$B$35+H17*Supuestos!$B$27*Supuestos!$C$35+H17/(1+Supuestos!$B$26)*Supuestos!$B$28) -> 0.12711864 | N17: =IF(H17=0,0,H17/(1+Supuestos!$B$26)-K17-M17) -> 0.86425713 | O17: =IF(H17=0,0,H17/(1+Supuestos!$B$26)-L17-M17) -> 0.86425713 | P17: =G17*N17 -> 7920.9166 | Q17: =G17*O17 -> 7920.9166 | R17: =IF(H17=0,0,N17/(H17/(1+Supuestos!$B$26))) -> 0.31869482 | S17: =IF(H17=0,0,O17/(H17/(1+Supuestos!$B$26))) -> 0.31869482
A18: Colegios (quiosco) | B18: Pack de 6 | C18: =Costeo!C5 -> 6 | D18: =Mensual!$N$17 -> 9165 | E18: =Supuestos!C51 -> 0 | F18: =D18*E18 -> 0 | G18: =IF(C18=0,0,F18/C18) -> 0 | H18: =Supuestos!C43 -> 0 | I18: =G18*H18 -> 0 | J18: =I18/(1+Supuestos!$B$26) -> 0 | K18: =Costeo!C15 -> 9.8504318 | L18: =Costeo!D15 -> 9.3464318 | M18: =IF(H18=0,0,C18*Supuestos!$B$35+H18*Supuestos!$B$27*Supuestos!$C$35+H18/(1+Supuestos!$B$26)*Supuestos!$B$28) -> 0 | N18: =IF(H18=0,0,H18/(1+Supuestos!$B$26)-K18-M18) -> 0 | O18: =IF(H18=0,0,H18/(1+Supuestos!$B$26)-L18-M18) -> 0 | P18: =G18*N18 -> 0 | Q18: =G18*O18 -> 0 | R18: =IF(H18=0,0,N18/(H18/(1+Supuestos!$B$26))) -> 0 | S18: =IF(H18=0,0,O18/(H18/(1+Supuestos!$B$26))) -> 0
A19: Colegios (quiosco) | B19: Pack de 12 | C19: =Costeo!E5 -> 12 | D19: =Mensual!$N$17 -> 9165 | E19: =Supuestos!D51 -> 0 | F19: =D19*E19 -> 0 | G19: =IF(C19=0,0,F19/C19) -> 0 | H19: =Supuestos!D43 -> 0 | I19: =G19*H19 -> 0 | J19: =I19/(1+Supuestos!$B$26) -> 0 | K19: =Costeo!E15 -> 18.524864 | L19: =Costeo!E15 -> 18.524864 | M19: =IF(H19=0,0,C19*Supuestos!$B$35+H19*Supuestos!$B$27*Supuestos!$C$35+H19/(1+Supuestos!$B$26)*Supuestos!$B$28) -> 0 | N19: =IF(H19=0,0,H19/(1+Supuestos!$B$26)-K19-M19) -> 0 | O19: =IF(H19=0,0,H19/(1+Supuestos!$B$26)-L19-M19) -> 0 | P19: =G19*N19 -> 0 | Q19: =G19*O19 -> 0 | R19: =IF(H19=0,0,N19/(H19/(1+Supuestos!$B$26))) -> 0 | S19: =IF(H19=0,0,O19/(H19/(1+Supuestos!$B$26))) -> 0
A20: Colegios (quiosco) | B20: Caja de 3 sabores | C20: =Costeo!F5 -> 3 | D20: =Mensual!$N$17 -> 9165 | E20: =Supuestos!E51 -> 0 | F20: =D20*E20 -> 0 | G20: =IF(C20=0,0,F20/C20) -> 0 | H20: =Supuestos!E43 -> 0 | I20: =G20*H20 -> 0 | J20: =I20/(1+Supuestos!$B$26) -> 0 | K20: =Costeo!F15 -> 5.0249659 | L20: =Costeo!F15 -> 5.0249659 | M20: =IF(H20=0,0,C20*Supuestos!$B$35+H20*Supuestos!$B$27*Supuestos!$C$35+H20/(1+Supuestos!$B$26)*Supuestos!$B$28) -> 0 | N20: =IF(H20=0,0,H20/(1+Supuestos!$B$26)-K20-M20) -> 0 | O20: =IF(H20=0,0,H20/(1+Supuestos!$B$26)-L20-M20) -> 0 | P20: =G20*N20 -> 0 | Q20: =G20*O20 -> 0 | R20: =IF(H20=0,0,N20/(H20/(1+Supuestos!$B$26))) -> 0 | S20: =IF(H20=0,0,O20/(H20/(1+Supuestos!$B$26))) -> 0
A21: Tiendas naturistas | B21: Unidad individual | C21: =Costeo!B5 -> 1 | D21: =Mensual!$N$18 -> 3720 | E21: =Supuestos!B52 -> 0 | F21: =D21*E21 -> 0 | G21: =IF(C21=0,0,F21/C21) -> 0 | H21: =Supuestos!B44 -> 0 | I21: =G21*H21 -> 0 | J21: =I21/(1+Supuestos!$B$26) -> 0 | K21: =Costeo!B15 -> 1.7204886 | L21: =Costeo!B15 -> 1.7204886 | M21: =IF(H21=0,0,C21*Supuestos!$B$36+H21*Supuestos!$B$27*Supuestos!$C$36+H21/(1+Supuestos!$B$26)*Supuestos!$B$28) -> 0 | N21: =IF(H21=0,0,H21/(1+Supuestos!$B$26)-K21-M21) -> 0 | O21: =IF(H21=0,0,H21/(1+Supuestos!$B$26)-L21-M21) -> 0 | P21: =G21*N21 -> 0 | Q21: =G21*O21 -> 0 | R21: =IF(H21=0,0,N21/(H21/(1+Supuestos!$B$26))) -> 0 | S21: =IF(H21=0,0,O21/(H21/(1+Supuestos!$B$26))) -> 0
A22: Tiendas naturistas | B22: Pack de 6 | C22: =Costeo!C5 -> 6 | D22: =Mensual!$N$18 -> 3720 | E22: =Supuestos!C52 -> 1 | F22: =D22*E22 -> 3720 | G22: =IF(C22=0,0,F22/C22) -> 620 | H22: =Supuestos!C44 -> 18.5 | I22: =G22*H22 -> 11470 | J22: =I22/(1+Supuestos!$B$26) -> 9720.339 | K22: =Costeo!C15 -> 9.8504318 | L22: =Costeo!D15 -> 9.3464318 | M22: =IF(H22=0,0,C22*Supuestos!$B$36+H22*Supuestos!$B$27*Supuestos!$C$36+H22/(1+Supuestos!$B$26)*Supuestos!$B$28) -> 1.0567797 | N22: =IF(H22=0,0,H22/(1+Supuestos!$B$26)-K22-M22) -> 4.7707546 | O22: =IF(H22=0,0,H22/(1+Supuestos!$B$26)-L22-M22) -> 5.2747546 | P22: =G22*N22 -> 2957.8679 | Q22: =G22*O22 -> 3270.3479 | R22: =IF(H22=0,0,N22/(H22/(1+Supuestos!$B$26))) -> 0.30429678 | S22: =IF(H22=0,0,O22/(H22/(1+Supuestos!$B$26))) -> 0.33644381
A23: Tiendas naturistas | B23: Pack de 12 | C23: =Costeo!E5 -> 12 | D23: =Mensual!$N$18 -> 3720 | E23: =Supuestos!D52 -> 0 | F23: =D23*E23 -> 0 | G23: =IF(C23=0,0,F23/C23) -> 0 | H23: =Supuestos!D44 -> 0 | I23: =G23*H23 -> 0 | J23: =I23/(1+Supuestos!$B$26) -> 0 | K23: =Costeo!E15 -> 18.524864 | L23: =Costeo!E15 -> 18.524864 | M23: =IF(H23=0,0,C23*Supuestos!$B$36+H23*Supuestos!$B$27*Supuestos!$C$36+H23/(1+Supuestos!$B$26)*Supuestos!$B$28) -> 0 | N23: =IF(H23=0,0,H23/(1+Supuestos!$B$26)-K23-M23) -> 0 | O23: =IF(H23=0,0,H23/(1+Supuestos!$B$26)-L23-M23) -> 0 | P23: =G23*N23 -> 0 | Q23: =G23*O23 -> 0 | R23: =IF(H23=0,0,N23/(H23/(1+Supuestos!$B$26))) -> 0 | S23: =IF(H23=0,0,O23/(H23/(1+Supuestos!$B$26))) -> 0
A24: Tiendas naturistas | B24: Caja de 3 sabores | C24: =Costeo!F5 -> 3 | D24: =Mensual!$N$18 -> 3720 | E24: =Supuestos!E52 -> 0 | F24: =D24*E24 -> 0 | G24: =IF(C24=0,0,F24/C24) -> 0 | H24: =Supuestos!E44 -> 0 | I24: =G24*H24 -> 0 | J24: =I24/(1+Supuestos!$B$26) -> 0 | K24: =Costeo!F15 -> 5.0249659 | L24: =Costeo!F15 -> 5.0249659 | M24: =IF(H24=0,0,C24*Supuestos!$B$36+H24*Supuestos!$B$27*Supuestos!$C$36+H24/(1+Supuestos!$B$26)*Supuestos!$B$28) -> 0 | N24: =IF(H24=0,0,H24/(1+Supuestos!$B$26)-K24-M24) -> 0 | O24: =IF(H24=0,0,H24/(1+Supuestos!$B$26)-L24-M24) -> 0 | P24: =G24*N24 -> 0 | Q24: =G24*O24 -> 0 | R24: =IF(H24=0,0,N24/(H24/(1+Supuestos!$B$26))) -> 0 | S24: =IF(H24=0,0,O24/(H24/(1+Supuestos!$B$26))) -> 0
A25: Total | F25: =SUM(F5:F24) -> 52331 | I25: =SUM(I5:I24) -> 244728.18 | J25: =SUM(J5:J24) -> 207396.76 | P25: =SUM(P5:P24) -> 97293.745 | Q25: =SUM(Q5:Q24) -> 98932.698
A28: 2. Contribución por canal (la usan las hojas Mensual y Anio2)
A29: Canal | B29: Unidades | C29: Contribución — opción B | D29: Contribución — opción C | E29: Ingreso con IGV | F29: Contribución por unidad — B | G29: Contribución por unidad — C | H29: Ingreso con IGV por unidad
A30: Stands y carritos (malls y supermercados) | B30: =SUMIF($A$5:$A$24,A30,$F$5:$F$24) -> 22625 | C30: =SUMIF($A$5:$A$24,A30,$P$5:$P$24) -> 54614.797 | D30: =SUMIF($A$5:$A$24,A30,$Q$5:$Q$24) -> 55279.972 | E30: =SUMIF($A$5:$A$24,A30,$I$5:$I$24) -> 122033.59 | F30: =IF(B30=0,0,C30/B30) -> 2.4139137 | G30: =IF(B30=0,0,D30/B30) -> 2.4433137 | H30: =IF(B30=0,0,E30/B30) -> 5.39375
A31: Ferias y eventos | B31: =SUMIF($A$5:$A$24,A31,$F$5:$F$24) -> 7400 | C31: =SUMIF($A$5:$A$24,A31,$P$5:$P$24) -> 18673.881 | D31: =SUMIF($A$5:$A$24,A31,$Q$5:$Q$24) -> 18860.361 | E31: =SUMIF($A$5:$A$24,A31,$I$5:$I$24) -> 41033 | F31: =IF(B31=0,0,C31/B31) -> 2.5234974 | G31: =IF(B31=0,0,D31/B31) -> 2.5486974 | H31: =IF(B31=0,0,E31/B31) -> 5.545
A32: Recompra por WhatsApp e Instagram (delivery) | B32: =SUMIF($A$5:$A$24,A32,$F$5:$F$24) -> 9421 | C32: =SUMIF($A$5:$A$24,A32,$P$5:$P$24) -> 13126.283 | D32: =SUMIF($A$5:$A$24,A32,$Q$5:$Q$24) -> 13601.101 | E32: =SUMIF($A$5:$A$24,A32,$I$5:$I$24) -> 40863.588 | F32: =IF(B32=0,0,C32/B32) -> 1.3933003 | G32: =IF(B32=0,0,D32/B32) -> 1.4437003 | H32: =IF(B32=0,0,E32/B32) -> 4.3375
A33: Colegios (quiosco) | B33: =SUMIF($A$5:$A$24,A33,$F$5:$F$24) -> 9165 | C33: =SUMIF($A$5:$A$24,A33,$P$5:$P$24) -> 7920.9166 | D33: =SUMIF($A$5:$A$24,A33,$Q$5:$Q$24) -> 7920.9166 | E33: =SUMIF($A$5:$A$24,A33,$I$5:$I$24) -> 29328 | F33: =IF(B33=0,0,C33/B33) -> 0.86425713 | G33: =IF(B33=0,0,D33/B33) -> 0.86425713 | H33: =IF(B33=0,0,E33/B33) -> 3.2
A34: Tiendas naturistas | B34: =SUMIF($A$5:$A$24,A34,$F$5:$F$24) -> 3720 | C34: =SUMIF($A$5:$A$24,A34,$P$5:$P$24) -> 2957.8679 | D34: =SUMIF($A$5:$A$24,A34,$Q$5:$Q$24) -> 3270.3479 | E34: =SUMIF($A$5:$A$24,A34,$I$5:$I$24) -> 11470 | F34: =IF(B34=0,0,C34/B34) -> 0.79512577 | G34: =IF(B34=0,0,D34/B34) -> 0.87912577 | H34: =IF(B34=0,0,E34/B34) -> 3.0833333
A35: Total | B35: =SUM(B30:B34) -> 52331 | C35: =SUM(C30:C34) -> 97293.745 | D35: =SUM(D30:D34) -> 98932.698 | E35: =SUM(E30:E34) -> 244728.18 | F35: =IF(B35=0,0,C35/B35) -> 1.859199 | G35: =IF(B35=0,0,D35/B35) -> 1.890518 | H35: =IF(B35=0,0,E35/B35) -> 4.6765432
A37: 3. Resumen por presentación
A38: Presentación | B38: Unidades | C38: Envases vendidos | D38: Ingreso con IGV | E38: Contribución — opción B | F38: Contribución — opción C | G38: % de las unidades
A39: Unidad individual | B39: =SUMIF($B$5:$B$24,A39,$F$5:$F$24) -> 24917.5 | C39: =SUMIF($B$5:$B$24,A39,$G$5:$G$24) -> 24917.5 | D39: =SUMIF($B$5:$B$24,A39,$I$5:$I$24) -> 123843 | E39: =SUMIF($B$5:$B$24,A39,$P$5:$P$24) -> 53026.777 | F39: =SUMIF($B$5:$B$24,A39,$Q$5:$Q$24) -> 53026.777 | G39: =IF($F$25=0,0,B39/$F$25) -> 0.4761518
A40: Pack de 6 | B40: =SUMIF($B$5:$B$24,A40,$F$5:$F$24) -> 19511.35 | C40: =SUMIF($B$5:$B$24,A40,$G$5:$G$24) -> 3251.8917 | D40: =SUMIF($B$5:$B$24,A40,$I$5:$I$24) -> 83957.678 | E40: =SUMIF($B$5:$B$24,A40,$P$5:$P$24) -> 30110.138 | F40: =SUMIF($B$5:$B$24,A40,$Q$5:$Q$24) -> 31749.092 | G40: =IF($F$25=0,0,B40/$F$25) -> 0.37284497
A41: Pack de 12 | B41: =SUMIF($B$5:$B$24,A41,$F$5:$F$24) -> 3957.55 | C41: =SUMIF($B$5:$B$24,A41,$G$5:$G$24) -> 329.79583 | D41: =SUMIF($B$5:$B$24,A41,$I$5:$I$24) -> 16645.354 | E41: =SUMIF($B$5:$B$24,A41,$P$5:$P$24) -> 5637.7987 | F41: =SUMIF($B$5:$B$24,A41,$Q$5:$Q$24) -> 5637.7987 | G41: =IF($F$25=0,0,B41/$F$25) -> 0.075625346
A42: Caja de 3 sabores | B42: =SUMIF($B$5:$B$24,A42,$F$5:$F$24) -> 3944.6 | C42: =SUMIF($B$5:$B$24,A42,$G$5:$G$24) -> 1314.8667 | D42: =SUMIF($B$5:$B$24,A42,$I$5:$I$24) -> 20282.15 | E42: =SUMIF($B$5:$B$24,A42,$P$5:$P$24) -> 8519.0304 | F42: =SUMIF($B$5:$B$24,A42,$Q$5:$Q$24) -> 8519.0304 | G42: =IF($F$25=0,0,B42/$F$25) -> 0.075377883
A44: 4. Unidades por sabor en el año (para compras de insumos)
A45: Sabor | B45: % de las unidades | C45: Unidades en el año
A46: =Supuestos!A79 -> Chispa (choco clásico con chispas) | B46: =Supuestos!B79 -> 0.4 | C46: =$F$25*B46 -> 20932.4
A47: =Supuestos!A80 -> Andi (choco, plátano, canela y cañihua) | B47: =Supuestos!B80 -> 0.35 | C47: =$F$25*B47 -> 18315.85
A48: =Supuestos!A81 -> Lúcu (choco y lúcuma) | B48: =Supuestos!B81 -> 0.25 | C48: =$F$25*B48 -> 13082.75

Sheet Inversion
A1: Inversión inicial: todo lo necesario para vender desde el primer día
A2: Los documentos y permisos se pagan aquí, una sola vez. La proyección (hoja Mensual) supone que ya están listos al empezar las ventas en enero de 2027 (mes 1).
A4: Concepto | B4: S/ (sin IGV) | C4: Fuente o nota
A5: 1. Documentos y permisos para vender
A6: Constitución de AndiBite S.A.C. en un CDE de PRODUCE (notaría) | B6: 150 | C6: Documento 05
A7: RUC, Régimen MYPE Tributario, REMYPE y libro de reclamaciones virtual | B7: 0 | C7: SUNAT, PRODUCE e INDECOPI: sin costo
A8: Registro de marca en INDECOPI, clase 30 (tasa MYPE) | B8: 401.2 | C8: Documento 03
A9: Revisión legal del contrato de maquila (la S.A.C. es titular del registro sanitario) | B9: 400 | C9: Documento 05
A10: Análisis para el registro sanitario (3 sabores × S/600) | B10: 1800 | C10: Documento 05
A11: Perfil nutricional y hierro (3 × S/375) | B11: 1125 | C11: Documento 05
A12: Estudio de vida útil acelerado | B12: 1050 | C12: Documento 05
A13: Diseño y validación de la etiqueta (rotulado y Ley 30021) | B13: 650 | C13: Documento 05
A14: Registro sanitario DIGESA (tasa) | B14: 0 | C14: TUPA 2026: sin costo (Comunicado 05-2026-DIGESA)
A15: Carné de sanidad: requisito para contratar a vendedores y coordinador(a), que ya lo traen vigente | B15: 0 | C15: Ahorra S/75 (S/9 a 20 por persona, Andina). Verificar con cada mall o municipio que el carné del distrito del trabajador sea válido
A16: Póliza de responsabilidad civil para stands (1 año) | B16: 600 | C16: [HIPÓTESIS] Cotizar con una aseguradora; algunos malls la piden
A17: Subtotal documentos y permisos | B17: =SUM(B6:B16) -> 6176.2
A18: 2. Desarrollo del producto
A19: Pruebas caseras: insumos de 3 lotes | B19: 942.81 | C19: Documento 02
A20: Endulzantes para la versión sin octógono | B20: 148 | C20: Documento 05
A21: Análisis preliminar de azúcar y hierro (2 × S/375) | B21: 750 | C21: Documento 05
A22: Prueba sensorial con niños | B22: 150 | C22: Documento 05
A23: Desarrollo y lote piloto en la planta | B23: 1750 | C23: [POR CONFIRMAR] Documento 05
A24: Subtotal desarrollo | B24: =SUM(B19:B23) -> 3740.81
A25: 3. Marca, app y puntos de venta
A26: Identidad de marca | B26: 800 | C26: Documento 05
A27: Fotos de producto | B27: 300 | C27: Documento 05
A28: Web, dominio y app Andi, Misión Hierro (terminar, probar con familias y publicar) | B28: 2150 | C28: Web y dominio S/150 (documento 05) más S/2,000 para la app: el prototipo funcional ya está hecho (carpeta app-andi-mision-hierro); falta conectar el laboratorio real, probar con 10 familias, revisión legal y publicación (documento 09)
A29: Subtotal marca | B29: =SUM(B26:B28) -> 3250
A30: 4. Arranque de la operación
A31: Empaque inicial (mínimos de compra) | B31: 3150 | C31: Documento 05, más S/120 de los códigos únicos de la app en las primeras 3,000 etiquetas
A32: Stock inicial para enero y febrero | B32: 4800.7 | C32: Documento 05, actualizado al costo con sangrecita en polvo (pack de 6 de S/8.29 a S/9.62)
A33: Marketing de lanzamiento (degustaciones, influencers, POP) | B33: 3204 | C33: Documento 05
A34: Capital de trabajo (2 meses) | B34: 8000 | C34: Documento 05
A35: Subtotal arranque | B35: =SUM(B31:B34) -> 19154.7
A36: 5. Activos que se deprecian
A37: Equipos mínimos y carrito de exhibición con gráfica | B37: =B38+B39 -> 4838
A38: Equipos mínimos (balanza, selladora, coolers, kit de feria, POS) | B38: 2338 | C38: Documento 05
A39: 1 carrito de exhibición con vitrina y gráfica (los otros puntos usan el kit de feria o el módulo del mall) | B39: 2500 | C39: Melamina a medida S/1,150 a 1,350 por metro lineal, más vitrina y gráfica (documento 08)
A41: Imprevistos (10 % de todo lo anterior) | B41: =0.1*(B17+B24+B29+B35+B37) -> 3715.971
A42: INVERSIÓN TOTAL | B42: =B17+B24+B29+B35+B37+B41 -> 40875.681
A44: Financiamiento
A45: Fuente | B45: S/ | C45: Nota
A46: Aporte de los 5 socios | B46: 25000 | C46: S/5,000 cada uno (documento 05)
A47: Préstamo | B47: =MAX(0,CEILING(B42-B46,500)) -> 16000 | C47: Lo que falta, redondeado a S/500
A48: Tasa efectiva anual del préstamo | B48: 0.35 | C48: [POR CONFIRMAR] Comparar tasas de microempresa en la SBS
A49: Número de cuotas mensuales | B49: 24 | C49: 24 cuotas: con 12, la cuota (unos S/1,560) se come la caja de los primeros meses
A50: Cuota mensual | B50: =PMT((1+B48)^(1/12)-1,B49,-B47) -> 897.81095
A51: Intereses totales del préstamo | B51: =B50*B49-B47 -> 5547.4629
A52: Caja que sobra después de financiar la inversión | B52: =B46+B47-B42 -> 124.319
A53: Línea de crédito de respaldo (no se usa en el plan base) | B53: 3000 | C53: Se abre con el banco del préstamo y solo se usa si las ventas bajan (con 20 % menos ventas por punto la caja más baja del año 1 llegaría a unos −S/2,200). Sin costo mientras no se use [POR CONFIRMAR con el banco]

Sheet Mensual
A1: Proyección mensual del año 1 (mes 1 = enero de 2027), escenario base
A2: Supone que los documentos y permisos ya están listos (su costo está en la hoja Inversion). La venta física es el canal principal; WhatsApp queda para la recompra. Cambie los datos azules para probar otro escenario.
A4: Actividad comercial del mes (datos) | B4: M1 Ene-27 | C4: M2 Feb-27 | D4: M3 Mar-27 | E4: M4 Abr-27 | F4: M5 May-27 | G4: M6 Jun-27 | H4: M7 Jul-27 | I4: M8 Ago-27 | J4: M9 Set-27 | K4: M10 Oct-27 | L4: M11 Nov-27 | M4: M12 Dic-27 | N4: Total año
A5: Puntos de venta con stand o carrito (fines de semana) | B5: 1 | C5: 2 | D5: 2 | E5: 2 | F5: 2 | G5: 2 | H5: 2 | I5: 3 | J5: 3 | K5: 3 | L5: 3 | M5: 3 | N5: =SUM(B5:M5) -> 28
A6: Días de atención por punto en el mes | B6: 9 | C6: 9 | D6: 9 | E6: 9 | F6: 9 | G6: 9 | H6: 10 | I6: 9 | J6: 9 | K6: 9 | L6: 9 | M6: 12 | N6: =SUM(B6:M6) -> 112
A7: Brownies vendidos por día en cada punto (meta: 80 o más) | B7: 50 | C7: 80 | D7: 100 | E7: 80 | F7: 85 | G7: 80 | H7: 85 | I7: 85 | J7: 90 | K7: 90 | L7: 90 | M7: 90 | N7: =SUM(B7:M7) -> 1005
A8: Ferias pagadas en el mes (campaña escolar en febrero y Día del Niño en abril) | B8: 0 | C8: 1 | D8: 0 | E8: 1 | F8: 0 | G8: 0 | H8: 0 | I8: 0 | J8: 0 | K8: 0 | L8: 0 | M8: 0 | N8: =SUM(B8:M8) -> 2
A9: Eventos sin costo (kermeses, cumpleaños, ferias saludables y municipales) | B9: 1 | C9: 2 | D9: 4 | E9: 4 | F9: 5 | G9: 4 | H9: 3 | I9: 4 | J9: 4 | K9: 4 | L9: 3 | M9: 2 | N9: =SUM(B9:M9) -> 40
A10: Unidades a colegios (quiosco; año escolar de marzo a mediados de diciembre) | B10: 0 | C10: 0 | D10: 300 | E10: 600 | F10: 765 | G10: 900 | H10: 600 | I10: 1200 | J10: 1200 | K10: 1500 | L10: 1500 | M10: 600 | N10: =SUM(B10:M10) -> 9165
A11: Unidades a tiendas naturistas | B11: 120 | C11: 180 | D11: 180 | E11: 240 | F11: 300 | G11: 300 | H11: 360 | I11: 360 | J11: 360 | K11: 420 | L11: 420 | M11: 480 | N11: =SUM(B11:M11) -> 3720
A13: Unidades vendidas por canal | B13: M1 Ene-27 | C13: M2 Feb-27 | D13: M3 Mar-27 | E13: M4 Abr-27 | F13: M5 May-27 | G13: M6 Jun-27 | H13: M7 Jul-27 | I13: M8 Ago-27 | J13: M9 Set-27 | K13: M10 Oct-27 | L13: M11 Nov-27 | M13: M12 Dic-27 | N13: Total año
A14: Stands y carritos (malls y supermercados) | B14: =B5*B6*B7 -> 450 | C14: =C5*C6*C7 -> 1440 | D14: =D5*D6*D7 -> 1800 | E14: =E5*E6*E7 -> 1440 | F14: =F5*F6*F7 -> 1530 | G14: =G5*G6*G7 -> 1440 | H14: =H5*H6*H7 -> 1700 | I14: =I5*I6*I7 -> 2295 | ... M14: =M5*M6*M7 -> 3240 | N14: =SUM(B14:M14) -> 22625
A15: Ferias y eventos | B15: =B8*Supuestos!$B$62+B9*Supuestos!$B$63 -> 150 | C15: =C8*Supuestos!$B$62+C9*Supuestos!$B$63 -> 1000 | D15: =D8*Supuestos!$B$62+D9*Supuestos!$B$63 -> 600 | E15: =E8*Supuestos!$B$62+E9*Supuestos!$B$63 -> 1300 | F15: =F8*Supuestos!$B$62+F9*Supuestos!$B$63 -> 750 | G15: =G8*Supuestos!$B$62+G9*Supuestos!$B$63 -> 600 | H15: =H8*Supuestos!$B$62+H9*Supuestos!$B$63 -> 450 | I15: =I8*Supuestos!$B$62+I9*Supuestos!$B$63 -> 600 | ... M15: =M8*Supuestos!$B$62+M9*Supuestos!$B$63 -> 300 | N15: =SUM(B15:M15) -> 7400
A16: Recompra por WhatsApp e Instagram (delivery) | B16: =Supuestos!$B$66 -> 150 | C16: =ROUND(Supuestos!$B$65*(B14+B15),0) -> 210 | D16: =ROUND(Supuestos!$B$65*(C14+C15),0) -> 854 | E16: =ROUND(Supuestos!$B$65*(D14+D15),0) -> 840 | F16: =ROUND(Supuestos!$B$65*(E14+E15),0) -> 959 | G16: =ROUND(Supuestos!$B$65*(F14+F15),0) -> 798 | H16: =ROUND(Supuestos!$B$65*(G14+G15),0) -> 714 | I16: =ROUND(Supuestos!$B$65*(H14+H15),0) -> 753 | J16: =ROUND(Supuestos!$B$65*(I14+I15),0) -> 1013 | ... M16: =ROUND(Supuestos!$B$65*(L14+L15),0) -> 1008 | N16: =SUM(B16:M16) -> 9421
A17: Colegios (quiosco) | B17: =B10 -> 0 | C17: =C10 -> 0 | D17: =D10 -> 300 | E17: =E10 -> 600 | F17: =F10 -> 765 | G17: =G10 -> 900 | H17: =H10 -> 600 | I17: =I10 -> 1200 | ... M17: =M10 -> 600 | N17: =SUM(B17:M17) -> 9165
A18: Tiendas naturistas | B18: =B11 -> 120 | C18: =C11 -> 180 | D18: =D11 -> 180 | E18: =E11 -> 240 | F18: =F11 -> 300 | G18: =G11 -> 300 | H18: =H11 -> 360 | I18: =I11 -> 360 | ... M18: =M11 -> 480 | N18: =SUM(B18:M18) -> 3720
A19: Total unidades | B19: =SUM(B14:B18) -> 870 | C19: =SUM(C14:C18) -> 2830 | D19: =SUM(D14:D18) -> 3734 | E19: =SUM(E14:E18) -> 4420 | F19: =SUM(F14:F18) -> 4304 | G19: =SUM(G14:G18) -> 4038 | H19: =SUM(H14:H18) -> 3824 | I19: =SUM(I14:I18) -> 5208 | ... N19: =SUM(N14:N18) -> 52331
A21: Producción que hay que pedir a la planta
A22: Unidades individuales sueltas | B22: =SUMPRODUCT(B$14:B$18,Supuestos!$B$48:$B$52) -> 315 | C22: =SUMPRODUCT(C$14:C$18,Supuestos!$B$48:$B$52) -> 1320 | D22: =SUMPRODUCT(D$14:D$18,Supuestos!$B$48:$B$52) -> 1560 | E22: =SUMPRODUCT(E$14:E$18,Supuestos!$B$48:$B$52) -> 2100 | F22: =SUMPRODUCT(F$14:F$18,Supuestos!$B$48:$B$52) -> 1980 | G22: =SUMPRODUCT(G$14:G$18,Supuestos!$B$48:$B$52) -> 1980 | H22: =SUMPRODUCT(H$14:H$18,Supuestos!$B$48:$B$52) -> 1720 | I22: =SUMPRODUCT(I$14:I$18,Supuestos!$B$48:$B$52) -> 2707.5 | ... M22: =SUMPRODUCT(M$14:M$18,Supuestos!$B$48:$B$52) -> 2400 | N22: =SUM(B22:M22) -> 24917.5
A23: Unidades que van en packs de 6 | B23: =SUMPRODUCT(B$14:B$18,Supuestos!$C$48:$C$52) -> 412.5 | C23: =SUMPRODUCT(C$14:C$18,Supuestos!$C$48:$C$52) -> 1110 | D23: =SUMPRODUCT(D$14:D$18,Supuestos!$C$48:$C$52) -> 1502.4 | E23: =SUMPRODUCT(E$14:E$18,Supuestos!$C$48:$C$52) -> 1638 | F23: =SUMPRODUCT(F$14:F$18,Supuestos!$C$48:$C$52) -> 1635.9 | G23: =SUMPRODUCT(G$14:G$18,Supuestos!$C$48:$C$52) -> 1462.8 | H23: =SUMPRODUCT(H$14:H$18,Supuestos!$C$48:$C$52) -> 1518.4 | I23: =SUMPRODUCT(I$14:I$18,Supuestos!$C$48:$C$52) -> 1795.05 | ... M23: =SUMPRODUCT(M$14:M$18,Supuestos!$C$48:$C$52) -> 2308.8 | N23: =SUM(B23:M23) -> 19511.35
A24: Unidades que van en packs de 12 | B24: =SUMPRODUCT(B$14:B$18,Supuestos!$D$48:$D$52) -> 67.5 | C24: =SUMPRODUCT(C$14:C$18,Supuestos!$D$48:$D$52) -> 135 | D24: =SUMPRODUCT(D$14:D$18,Supuestos!$D$48:$D$52) -> 346.2 | E24: =SUMPRODUCT(E$14:E$18,Supuestos!$D$48:$D$52) -> 324 | F24: =SUMPRODUCT(F$14:F$18,Supuestos!$D$48:$D$52) -> 364.2 | G24: =SUMPRODUCT(G$14:G$18,Supuestos!$D$48:$D$52) -> 311.4 | H24: =SUMPRODUCT(H$14:H$18,Supuestos!$D$48:$D$52) -> 299.2 | I24: =SUMPRODUCT(I$14:I$18,Supuestos!$D$48:$D$52) -> 340.65 | ... M24: =SUMPRODUCT(M$14:M$18,Supuestos!$D$48:$D$52) -> 464.4 | N24: =SUM(B24:M24) -> 3957.55
A25: Packs de 6 a armar | B25: =B23/Costeo!$C$5 -> 68.75 | C25: =C23/Costeo!$C$5 -> 185 | D25: =D23/Costeo!$C$5 -> 250.4 | E25: =E23/Costeo!$C$5 -> 273 | F25: =F23/Costeo!$C$5 -> 272.65 | G25: =G23/Costeo!$C$5 -> 243.8 | H25: =H23/Costeo!$C$5 -> 253.06667 | I25: =I23/Costeo!$C$5 -> 299.175 | ... M25: =M23/Costeo!$C$5 -> 384.8 | N25: =SUM(B25:M25) -> 3251.8917
A26: Packs de 12 a armar | B26: =B24/Costeo!$E$5 -> 5.625 | C26: =C24/Costeo!$E$5 -> 11.25 | D26: =D24/Costeo!$E$5 -> 28.85 | E26: =E24/Costeo!$E$5 -> 27 | F26: =F24/Costeo!$E$5 -> 30.35 | G26: =G24/Costeo!$E$5 -> 25.95 | H26: =H24/Costeo!$E$5 -> 24.933333 | I26: =I24/Costeo!$E$5 -> 28.3875 | ... M26: =M24/Costeo!$E$5 -> 38.7 | N26: =SUM(B26:M26) -> 329.79583
A28: Resultado mensual (S/ sin IGV, salvo la primera fila)
A29: Ventas con IGV | B29: =SUMPRODUCT(B$14:B$18,Proyeccion!$H$30:$H$34) -> 4279.5625 | C29: =SUMPRODUCT(C$14:C$18,Proyeccion!$H$30:$H$34) -> 14777.875 | D29: =SUMPRODUCT(D$14:D$18,Proyeccion!$H$30:$H$34) -> 18254.975 | E29: =SUMPRODUCT(E$14:E$18,Proyeccion!$H$30:$H$34) -> 21279 | F29: =SUMPRODUCT(F$14:F$18,Proyeccion!$H$30:$H$34) -> 19943.85 | G29: =SUMPRODUCT(G$14:G$18,Proyeccion!$H$30:$H$34) -> 18360.325 | H29: =SUMPRODUCT(H$14:H$18,Proyeccion!$H$30:$H$34) -> 17791.6 | I29: =SUMPRODUCT(I$14:I$18,Proyeccion!$H$30:$H$34) -> 23921.794 | ... M29: =SUMPRODUCT(M$14:M$18,Proyeccion!$H$30:$H$34) -> 26911.45 | N29: =SUM(B29:M29) -> 244728.18
A30: Ventas sin IGV | B30: =B29/(1+Supuestos!$B$26) -> 3626.7479 | C30: =C29/(1+Supuestos!$B$26) -> 12523.623 | D30: =D29/(1+Supuestos!$B$26) -> 15470.318 | E30: =E29/(1+Supuestos!$B$26) -> 18033.051 | F30: =F29/(1+Supuestos!$B$26) -> 16901.568 | G30: =G29/(1+Supuestos!$B$26) -> 15559.597 | H30: =H29/(1+Supuestos!$B$26) -> 15077.627 | I30: =I29/(1+Supuestos!$B$26) -> 20272.707 | ... M30: =M29/(1+Supuestos!$B$26) -> 22806.314 | N30: =SUM(B30:M30) -> 207396.76
A31: Contribución con pack de 6 opción B | B31: =SUMPRODUCT(B$14:B$18,Proyeccion!$F$30:$F$34) -> 1769.1959 | C31: =SUMPRODUCT(C$14:C$18,Proyeccion!$F$30:$F$34) -> 6435.2488 | D31: =SUMPRODUCT(D$14:D$18,Proyeccion!$F$30:$F$34) -> 7451.4214 | E31: =SUMPRODUCT(E$14:E$18,Proyeccion!$F$30:$F$34) -> 8636.3391 | F31: =SUMPRODUCT(F$14:F$18,Proyeccion!$F$30:$F$34) -> 7821.7805 | G31: =SUMPRODUCT(G$14:G$18,Proyeccion!$F$30:$F$34) -> 7118.357 | H31: =SUMPRODUCT(H$14:H$18,Proyeccion!$F$30:$F$34) -> 7038.8431 | I31: =SUMPRODUCT(I$14:I$18,Proyeccion!$F$30:$F$34) -> 9426.5393 | ... M31: =SUMPRODUCT(M$14:M$18,Proyeccion!$F$30:$F$34) -> 10882.791 | N31: =SUM(B31:M31) -> 97293.745
A32: Contribución con pack de 6 opción C | B32: =SUMPRODUCT(B$14:B$18,Proyeccion!$G$30:$G$34) -> 1803.8459 | C32: =SUMPRODUCT(C$14:C$18,Proyeccion!$G$30:$G$34) -> 6528.4888 | D32: =SUMPRODUCT(D$14:D$18,Proyeccion!$G$30:$G$34) -> 7577.623 | E32: =SUMPRODUCT(E$14:E$18,Proyeccion!$G$30:$G$34) -> 8773.9311 | F32: =SUMPRODUCT(F$14:F$18,Proyeccion!$G$30:$G$34) -> 7959.1961 | G32: =SUMPRODUCT(G$14:G$18,Proyeccion!$G$30:$G$34) -> 7241.2322 | H32: =SUMPRODUCT(H$14:H$18,Proyeccion!$G$30:$G$34) -> 7166.3887 | I32: =SUMPRODUCT(I$14:I$18,Proyeccion!$G$30:$G$34) -> 9577.3235 | ... M32: =SUMPRODUCT(M$14:M$18,Proyeccion!$G$30:$G$34) -> 11076.73 | N32: =SUM(B32:M32) -> 98932.698
A33: Espacio para stands y carrito | B33: =B5*Supuestos!$B$57 -> 600 | C33: =C5*Supuestos!$B$57 -> 1200 | D33: =D5*Supuestos!$B$57 -> 1200 | E33: =E5*Supuestos!$B$57 -> 1200 | F33: =F5*Supuestos!$B$57 -> 1200 | G33: =G5*Supuestos!$B$57 -> 1200 | H33: =H5*Supuestos!$B$57 -> 1200 | I33: =I5*Supuestos!$B$57 -> 1800 | ... M33: =M5*Supuestos!$B$57 -> 1800 | N33: =SUM(B33:M33) -> 16800
A34: Vendedores de stand (por día de atención) | B34: =MAX(0,B5-Supuestos!$B$59)*B6*Supuestos!$B$58 -> 810 | C34: =MAX(0,C5-Supuestos!$B$59)*C6*Supuestos!$B$58 -> 1620 | D34: =MAX(0,D5-Supuestos!$B$59)*D6*Supuestos!$B$58 -> 1620 | E34: =MAX(0,E5-Supuestos!$B$59)*E6*Supuestos!$B$58 -> 1620 | F34: =MAX(0,F5-Supuestos!$B$59)*F6*Supuestos!$B$58 -> 1620 | G34: =MAX(0,G5-Supuestos!$B$59)*G6*Supuestos!$B$58 -> 1620 | H34: =MAX(0,H5-Supuestos!$B$59)*H6*Supuestos!$B$58 -> 1800 | I34: =MAX(0,I5-Supuestos!$B$59)*I6*Supuestos!$B$58 -> 2430 | ... M34: =MAX(0,M5-Supuestos!$B$59)*M6*Supuestos!$B$58 -> 3240 | N34: =SUM(B34:M34) -> 23670
A35: Ferias pagadas (stand y vendedor(a) los días de la feria) | B35: =B8*(Supuestos!$B$60+Supuestos!$B$61*Supuestos!$B$58) -> 0 | C35: =C8*(Supuestos!$B$60+Supuestos!$B$61*Supuestos!$B$58) -> 2070 | D35: =D8*(Supuestos!$B$60+Supuestos!$B$61*Supuestos!$B$58) -> 0 | E35: =E8*(Supuestos!$B$60+Supuestos!$B$61*Supuestos!$B$58) -> 2070 | F35: =F8*(Supuestos!$B$60+Supuestos!$B$61*Supuestos!$B$58) -> 0 | G35: =G8*(Supuestos!$B$60+Supuestos!$B$61*Supuestos!$B$58) -> 0 | H35: =H8*(Supuestos!$B$60+Supuestos!$B$61*Supuestos!$B$58) -> 0 | I35: =I8*(Supuestos!$B$60+Supuestos!$B$61*Supuestos!$B$58) -> 0 | ... M35: =M8*(Supuestos!$B$60+Supuestos!$B$61*Supuestos!$B$58) -> 0 | N35: =SUM(B35:M35) -> 4140
A36: Eventos sin costo (vendedor(a) 1 día y aporte al organizador) | B36: =B9*(Supuestos!$B$58+Supuestos!$B$64) -> 160 | C36: =C9*(Supuestos!$B$58+Supuestos!$B$64) -> 320 | D36: =D9*(Supuestos!$B$58+Supuestos!$B$64) -> 640 | E36: =E9*(Supuestos!$B$58+Supuestos!$B$64) -> 640 | F36: =F9*(Supuestos!$B$58+Supuestos!$B$64) -> 800 | G36: =G9*(Supuestos!$B$58+Supuestos!$B$64) -> 640 | H36: =H9*(Supuestos!$B$58+Supuestos!$B$64) -> 480 | I36: =I9*(Supuestos!$B$58+Supuestos!$B$64) -> 640 | ... M36: =M9*(Supuestos!$B$58+Supuestos!$B$64) -> 320 | N36: =SUM(B36:M36) -> 6400
A37: Costos fijos del mes | B37: =Supuestos!$B$75 -> 2738.3889 | C37: =Supuestos!$B$75 -> 2738.3889 | D37: =Supuestos!$B$75 -> 2738.3889 | E37: =Supuestos!$B$75 -> 2738.3889 | F37: =Supuestos!$B$75 -> 2738.3889 | G37: =Supuestos!$B$75 -> 2738.3889 | H37: =Supuestos!$B$75 -> 2738.3889 | I37: =Supuestos!$B$75 -> 2738.3889 | ... M37: =Supuestos!$B$75 -> 2738.3889 | N37: =SUM(B37:M37) -> 32860.667
A38: Resultado operativo — opción B | B38: =B31-SUM(B33:B37) -> -2539.193 | C38: =C31-SUM(C33:C37) -> -1513.1401 | D38: =D31-SUM(D33:D37) -> 1253.0325 | E38: =E31-SUM(E33:E37) -> 367.95018 | F38: =F31-SUM(F33:F37) -> 1463.3916 | G38: =G31-SUM(G33:G37) -> 919.96808 | H38: =H31-SUM(H33:H37) -> 820.45421 | I38: =I31-SUM(I33:I37) -> 1818.1505 | ... M38: =M31-SUM(M33:M37) -> 2784.4021 | N38: =SUM(B38:M38) -> 13423.078
A39: Resultado operativo — opción C | B39: =B32-SUM(B33:B37) -> -2504.543 | C39: =C32-SUM(C33:C37) -> -1419.9001 | D39: =D32-SUM(D33:D37) -> 1379.2341 | E39: =E32-SUM(E33:E37) -> 505.54218 | F39: =F32-SUM(F33:F37) -> 1600.8072 | G39: =G32-SUM(G33:G37) -> 1042.8433 | H39: =H32-SUM(H33:H37) -> 947.99981 | I39: =I32-SUM(I33:I37) -> 1968.9347 | ... M39: =M32-SUM(M33:M37) -> 2978.3413 | N39: =SUM(B39:M39) -> 15062.032
A40: Resultado acumulado — opción B | B40: =B38 -> -2539.193 | C40: =B40+C38 -> -4052.3331 | D40: =C40+D38 -> -2799.3006 | E40: =D40+E38 -> -2431.3504 | F40: =E40+F38 -> -967.95885 | G40: =F40+G38 -> -47.990769 | H40: =G40+H38 -> 772.46344 | I40: =H40+I38 -> 2590.6139 | J40: =I40+J38 -> 5096.9008 | ... M40: =L40+M38 -> 13423.078
A41: Resultado acumulado — opción C | B41: =B39 -> -2504.543 | C41: =B41+C39 -> -3924.4431 | D41: =C41+D39 -> -2545.209 | E41: =D41+E39 -> -2039.6668 | F41: =E41+F39 -> -438.85965 | G41: =F41+G39 -> 603.98363 | H41: =G41+H39 -> 1551.9834 | I41: =H41+I39 -> 3520.9181 | J41: =I41+J39 -> 6195.0622 | ... M41: =L41+M39 -> 15062.032
A42: Cuota del préstamo | B42: =IF(1<=Inversion!$B$49,Inversion!$B$50,0) -> 897.81095 | C42: =IF(2<=Inversion!$B$49,Inversion!$B$50,0) -> 897.81095 | D42: =IF(3<=Inversion!$B$49,Inversion!$B$50,0) -> 897.81095 | E42: =IF(4<=Inversion!$B$49,Inversion!$B$50,0) -> 897.81095 | F42: =IF(5<=Inversion!$B$49,Inversion!$B$50,0) -> 897.81095 | G42: =IF(6<=Inversion!$B$49,Inversion!$B$50,0) -> 897.81095 | H42: =IF(7<=Inversion!$B$49,Inversion!$B$50,0) -> 897.81095 | I42: =IF(8<=Inversion!$B$49,Inversion!$B$50,0) -> 897.81095 | J42: =IF(9<=Inversion!$B$49,Inversion!$B$50,0) -> 897.81095 | K42: =IF(10<=Inversion!$B$49,Inversion!$B$50,0) -> 897.81095 | L42: =IF(11<=Inversion!$B$49,Inversion!$B$50,0) -> 897.81095 | M42: =IF(12<=Inversion!$B$49,Inversion!$B$50,0) -> 897.81095 | N42: =SUM(B42:M42) -> 10773.731
A43: Depreciación (no sale de caja) | B43: =Supuestos!$B$74 -> 134.38889 | C43: =Supuestos!$B$74 -> 134.38889 | D43: =Supuestos!$B$74 -> 134.38889 | E43: =Supuestos!$B$74 -> 134.38889 | F43: =Supuestos!$B$74 -> 134.38889 | G43: =Supuestos!$B$74 -> 134.38889 | H43: =Supuestos!$B$74 -> 134.38889 | I43: =Supuestos!$B$74 -> 134.38889 | ... M43: =Supuestos!$B$74 -> 134.38889 | N43: =SUM(B43:M43) -> 1612.6667
A44: Caja al cierre del mes (capital de trabajo y lo que sobra de la inversión, más el resultado, más la depreciación, menos la cuota) | B44: =Inversion!$B$34+Inversion!$B$52+B38+B43-B42 -> 4821.704 | C44: =B44+C38+C43-C42 -> 2545.1418 | D44: =C44+D38+D43-D42 -> 3034.7522 | E44: =D44+E38+E43-E42 -> 2639.2803 | F44: =E44+F38+F43-F42 -> 3339.2498 | G44: =F44+G38+G43-G42 -> 3495.7958 | H44: =G44+H38+H43-H42 -> 3552.828 | I44: =H44+I38+I43-I42 -> 4607.5564 | J44: =I44+J38+J43-J42 -> 6350.4212 | ... M44: =L44+M38+M43-M42 -> 12386.332
A46: La contribución multiplica las unidades de cada canal por la contribución por unidad de ese canal (hoja Proyeccion, tabla 2). Después se restan el espacio de los stands, los vendedores, las ferias pagadas, los eventos sin costo y los costos fijos. No incluye intereses del préstamo ni el impuesto a la renta anual.

Sheet Anio2
A1: Proyección del año 2 (enero a diciembre de 2028): los 3 puntos de venta todo el año
A2: Mismos precios, costos y mezcla que el año 1 (contribución por unidad de la hoja Proyeccion). No cuenta las mejoras que se activan solo si se cumplen sus reglas (4.º punto, maquila más barata, contrato anual del polvo): es un escenario prudente.
A4: Actividad comercial del mes (datos) | B4: M13 Ene-28 | C4: M14 Feb-28 | D4: M15 Mar-28 | E4: M16 Abr-28 | F4: M17 May-28 | G4: M18 Jun-28 | H4: M19 Jul-28 | I4: M20 Ago-28 | J4: M21 Set-28 | K4: M22 Oct-28 | L4: M23 Nov-28 | M4: M24 Dic-28 | N4: Total año 2
A5: Puntos de venta con stand o carrito (fines de semana) | B5: 3 | C5: 3 | D5: 3 | E5: 3 | F5: 3 | G5: 3 | H5: 3 | I5: 3 | J5: 3 | K5: 3 | L5: 3 | M5: 3 | N5: =SUM(B5:M5) -> 36
A6: Días de atención por punto en el mes | B6: 9 | C6: 9 | D6: 9 | E6: 9 | F6: 9 | G6: 9 | H6: 10 | I6: 9 | J6: 9 | K6: 9 | L6: 9 | M6: 12 | N6: =SUM(B6:M6) -> 112
A7: Brownies vendidos por día en cada punto (ritmo de fin del año 1) | B7: 80 | C7: 80 | D7: 90 | E7: 90 | F7: 90 | G7: 90 | H7: 90 | I7: 90 | J7: 90 | K7: 90 | L7: 90 | M7: 90 | N7: =SUM(B7:M7) -> 1060
A8: Ferias pagadas en el mes (campaña escolar y Día del Niño) | B8: 0 | C8: 1 | D8: 0 | E8: 1 | F8: 0 | G8: 0 | H8: 0 | I8: 0 | J8: 0 | K8: 0 | L8: 0 | M8: 0 | N8: =SUM(B8:M8) -> 2
A9: Eventos sin costo (kermeses, cumpleaños, ferias saludables y municipales) | B9: 2 | C9: 2 | D9: 4 | E9: 4 | F9: 4 | G9: 4 | H9: 3 | I9: 4 | J9: 4 | K9: 4 | L9: 4 | M9: 2 | N9: =SUM(B9:M9) -> 41
A10: Unidades a colegios (quiosco; año escolar completo) | B10: 0 | C10: 0 | D10: 1200 | E10: 1500 | F10: 1500 | G10: 1500 | H10: 900 | I10: 1500 | J10: 1500 | K10: 1500 | L10: 1500 | M10: 600 | N10: =SUM(B10:M10) -> 13200
A11: Unidades a tiendas naturistas | B11: 480 | C11: 480 | D11: 540 | E11: 540 | F11: 540 | G11: 600 | H11: 600 | I11: 600 | J11: 600 | K11: 660 | L11: 660 | M11: 660 | N11: =SUM(B11:M11) -> 6960
A13: Unidades vendidas por canal | B13: M13 Ene-28 | C13: M14 Feb-28 | D13: M15 Mar-28 | E13: M16 Abr-28 | F13: M17 May-28 | G13: M18 Jun-28 | H13: M19 Jul-28 | I13: M20 Ago-28 | J13: M21 Set-28 | K13: M22 Oct-28 | L13: M23 Nov-28 | M13: M24 Dic-28 | N13: Total año 2
A14: Stands y carritos (malls y supermercados) | B14: =B5*B6*B7 -> 2160 | C14: =C5*C6*C7 -> 2160 | D14: =D5*D6*D7 -> 2430 | E14: =E5*E6*E7 -> 2430 | F14: =F5*F6*F7 -> 2430 | G14: =G5*G6*G7 -> 2430 | H14: =H5*H6*H7 -> 2700 | I14: =I5*I6*I7 -> 2430 | ... M14: =M5*M6*M7 -> 3240 | N14: =SUM(B14:M14) -> 29700
A15: Ferias y eventos | B15: =B8*Supuestos!$B$62+B9*Supuestos!$B$63 -> 300 | C15: =C8*Supuestos!$B$62+C9*Supuestos!$B$63 -> 1000 | D15: =D8*Supuestos!$B$62+D9*Supuestos!$B$63 -> 600 | E15: =E8*Supuestos!$B$62+E9*Supuestos!$B$63 -> 1300 | F15: =F8*Supuestos!$B$62+F9*Supuestos!$B$63 -> 600 | G15: =G8*Supuestos!$B$62+G9*Supuestos!$B$63 -> 600 | H15: =H8*Supuestos!$B$62+H9*Supuestos!$B$63 -> 450 | I15: =I8*Supuestos!$B$62+I9*Supuestos!$B$63 -> 600 | ... M15: =M8*Supuestos!$B$62+M9*Supuestos!$B$63 -> 300 | N15: =SUM(B15:M15) -> 7550
A16: Recompra por WhatsApp e Instagram (delivery) | B16: =ROUND(Supuestos!$B$65*(Mensual!M14+Mensual!M15),0) -> 1239 | C16: =ROUND(Supuestos!$B$65*(B14+B15),0) -> 861 | D16: =ROUND(Supuestos!$B$65*(C14+C15),0) -> 1106 | E16: =ROUND(Supuestos!$B$65*(D14+D15),0) -> 1061 | F16: =ROUND(Supuestos!$B$65*(E14+E15),0) -> 1306 | G16: =ROUND(Supuestos!$B$65*(F14+F15),0) -> 1061 | H16: =ROUND(Supuestos!$B$65*(G14+G15),0) -> 1061 | I16: =ROUND(Supuestos!$B$65*(H14+H15),0) -> 1103 | J16: =ROUND(Supuestos!$B$65*(I14+I15),0) -> 1061 | ... M16: =ROUND(Supuestos!$B$65*(L14+L15),0) -> 1061 | N16: =SUM(B16:M16) -> 13042
A17: Colegios (quiosco) | B17: =B10 -> 0 | C17: =C10 -> 0 | D17: =D10 -> 1200 | E17: =E10 -> 1500 | F17: =F10 -> 1500 | G17: =G10 -> 1500 | H17: =H10 -> 900 | I17: =I10 -> 1500 | ... M17: =M10 -> 600 | N17: =SUM(B17:M17) -> 13200
A18: Tiendas naturistas | B18: =B11 -> 480 | C18: =C11 -> 480 | D18: =D11 -> 540 | E18: =E11 -> 540 | F18: =F11 -> 540 | G18: =G11 -> 600 | H18: =H11 -> 600 | I18: =I11 -> 600 | ... M18: =M11 -> 660 | N18: =SUM(B18:M18) -> 6960
A19: Total unidades | B19: =SUM(B14:B18) -> 4179 | C19: =SUM(C14:C18) -> 4501 | D19: =SUM(D14:D18) -> 5876 | E19: =SUM(E14:E18) -> 6831 | F19: =SUM(F14:F18) -> 6376 | G19: =SUM(G14:G18) -> 6191 | H19: =SUM(H14:H18) -> 5711 | I19: =SUM(I14:I18) -> 6233 | ... N19: =SUM(N14:N18) -> 70452
A21: Resultado mensual del año 2 (S/ sin IGV, salvo la primera fila; pack de 6 opción B)
A22: Ventas con IGV | B22: =SUMPRODUCT(B$14:B$18,Proyeccion!$H$30:$H$34) -> 20168.162 | C22: =SUMPRODUCT(C$14:C$18,Proyeccion!$H$30:$H$34) -> 22410.088 | D22: =SUMPRODUCT(D$14:D$18,Proyeccion!$H$30:$H$34) -> 26736.088 | E22: =SUMPRODUCT(E$14:E$18,Proyeccion!$H$30:$H$34) -> 31382.4 | F22: =SUMPRODUCT(F$14:F$18,Proyeccion!$H$30:$H$34) -> 28563.588 | G22: =SUMPRODUCT(G$14:G$18,Proyeccion!$H$30:$H$34) -> 27685.9 | H22: =SUMPRODUCT(H$14:H$18,Proyeccion!$H$30:$H$34) -> 26390.463 | I22: =SUMPRODUCT(I$14:I$18,Proyeccion!$H$30:$H$34) -> 27868.075 | ... M22: =SUMPRODUCT(M$14:M$18,Proyeccion!$H$30:$H$34) -> 27696.338 | N22: =SUM(B22:M22) -> 322328.8
A23: Ventas sin IGV | B23: =B22/(1+Supuestos!$B$26) -> 17091.663 | C23: =C22/(1+Supuestos!$B$26) -> 18991.6 | D23: =D22/(1+Supuestos!$B$26) -> 22657.701 | E23: =E22/(1+Supuestos!$B$26) -> 26595.254 | F23: =F22/(1+Supuestos!$B$26) -> 24206.43 | G23: =G22/(1+Supuestos!$B$26) -> 23462.627 | H23: =H22/(1+Supuestos!$B$26) -> 22364.799 | I23: =I22/(1+Supuestos!$B$26) -> 23617.013 | ... M23: =M22/(1+Supuestos!$B$26) -> 23471.472 | N23: =SUM(B23:M23) -> 273160
A24: Contribución | B24: =SUMPRODUCT(B$14:B$18,Proyeccion!$F$30:$F$34) -> 8079.0623 | C24: =SUMPRODUCT(C$14:C$18,Proyeccion!$F$30:$F$34) -> 9318.8429 | D24: =SUMPRODUCT(D$14:D$18,Proyeccion!$F$30:$F$34) -> 10387.375 | E24: =SUMPRODUCT(E$14:E$18,Proyeccion!$F$30:$F$34) -> 12350.402 | F24: =SUMPRODUCT(F$14:F$18,Proyeccion!$F$30:$F$34) -> 10925.313 | G24: =SUMPRODUCT(G$14:G$18,Proyeccion!$F$30:$F$34) -> 10631.662 | H24: =SUMPRODUCT(H$14:H$18,Proyeccion!$F$30:$F$34) -> 10386.339 | I24: =SUMPRODUCT(I$14:I$18,Proyeccion!$F$30:$F$34) -> 10690.18 | ... M24: =SUMPRODUCT(M$14:M$18,Proyeccion!$F$30:$F$34) -> 11099.759 | N24: =SUM(B24:M24) -> 125859.33
A25: Espacio para stands y carrito | B25: =B5*Supuestos!$B$57 -> 1800 | C25: =C5*Supuestos!$B$57 -> 1800 | D25: =D5*Supuestos!$B$57 -> 1800 | E25: =E5*Supuestos!$B$57 -> 1800 | F25: =F5*Supuestos!$B$57 -> 1800 | G25: =G5*Supuestos!$B$57 -> 1800 | H25: =H5*Supuestos!$B$57 -> 1800 | I25: =I5*Supuestos!$B$57 -> 1800 | ... M25: =M5*Supuestos!$B$57 -> 1800 | N25: =SUM(B25:M25) -> 21600
A26: Vendedores de stand | B26: =MAX(0,B5-Supuestos!$B$59)*B6*Supuestos!$B$58 -> 2430 | C26: =MAX(0,C5-Supuestos!$B$59)*C6*Supuestos!$B$58 -> 2430 | D26: =MAX(0,D5-Supuestos!$B$59)*D6*Supuestos!$B$58 -> 2430 | E26: =MAX(0,E5-Supuestos!$B$59)*E6*Supuestos!$B$58 -> 2430 | F26: =MAX(0,F5-Supuestos!$B$59)*F6*Supuestos!$B$58 -> 2430 | G26: =MAX(0,G5-Supuestos!$B$59)*G6*Supuestos!$B$58 -> 2430 | H26: =MAX(0,H5-Supuestos!$B$59)*H6*Supuestos!$B$58 -> 2700 | I26: =MAX(0,I5-Supuestos!$B$59)*I6*Supuestos!$B$58 -> 2430 | ... M26: =MAX(0,M5-Supuestos!$B$59)*M6*Supuestos!$B$58 -> 3240 | N26: =SUM(B26:M26) -> 30240
A27: Ferias pagadas | B27: =B8*(Supuestos!$B$60+Supuestos!$B$61*Supuestos!$B$58) -> 0 | C27: =C8*(Supuestos!$B$60+Supuestos!$B$61*Supuestos!$B$58) -> 2070 | D27: =D8*(Supuestos!$B$60+Supuestos!$B$61*Supuestos!$B$58) -> 0 | E27: =E8*(Supuestos!$B$60+Supuestos!$B$61*Supuestos!$B$58) -> 2070 | F27: =F8*(Supuestos!$B$60+Supuestos!$B$61*Supuestos!$B$58) -> 0 | G27: =G8*(Supuestos!$B$60+Supuestos!$B$61*Supuestos!$B$58) -> 0 | H27: =H8*(Supuestos!$B$60+Supuestos!$B$61*Supuestos!$B$58) -> 0 | I27: =I8*(Supuestos!$B$60+Supuestos!$B$61*Supuestos!$B$58) -> 0 | ... M27: =M8*(Supuestos!$B$60+Supuestos!$B$61*Supuestos!$B$58) -> 0 | N27: =SUM(B27:M27) -> 4140
A28: Eventos sin costo | B28: =B9*(Supuestos!$B$58+Supuestos!$B$64) -> 320 | C28: =C9*(Supuestos!$B$58+Supuestos!$B$64) -> 320 | D28: =D9*(Supuestos!$B$58+Supuestos!$B$64) -> 640 | E28: =E9*(Supuestos!$B$58+Supuestos!$B$64) -> 640 | F28: =F9*(Supuestos!$B$58+Supuestos!$B$64) -> 640 | G28: =G9*(Supuestos!$B$58+Supuestos!$B$64) -> 640 | H28: =H9*(Supuestos!$B$58+Supuestos!$B$64) -> 480 | I28: =I9*(Supuestos!$B$58+Supuestos!$B$64) -> 640 | ... M28: =M9*(Supuestos!$B$58+Supuestos!$B$64) -> 320 | N28: =SUM(B28:M28) -> 6560
A29: Costos fijos del mes | B29: =Supuestos!$B$75 -> 2738.3889 | C29: =Supuestos!$B$75 -> 2738.3889 | D29: =Supuestos!$B$75 -> 2738.3889 | E29: =Supuestos!$B$75 -> 2738.3889 | F29: =Supuestos!$B$75 -> 2738.3889 | G29: =Supuestos!$B$75 -> 2738.3889 | H29: =Supuestos!$B$75 -> 2738.3889 | I29: =Supuestos!$B$75 -> 2738.3889 | ... M29: =Supuestos!$B$75 -> 2738.3889 | N29: =SUM(B29:M29) -> 32860.667
A30: Resultado operativo | B30: =B24-SUM(B25:B29) -> 790.6734 | C30: =C24-SUM(C25:C29) -> -39.545961 | D30: =D24-SUM(D25:D29) -> 2778.9865 | E30: =E24-SUM(E25:E29) -> 2672.0133 | F30: =F24-SUM(F25:F29) -> 3316.9237 | G30: =G24-SUM(G25:G29) -> 3023.2726 | H30: =H24-SUM(H25:H29) -> 2667.9505 | I30: =I24-SUM(I25:I29) -> 3081.7913 | ... M30: =M24-SUM(M25:M29) -> 3001.3696 | N30: =SUM(B30:M30) -> 30458.668
A31: Resultado acumulado desde enero de 2027 | B31: =Mensual!N38+B30 -> 14213.752 | C31: =B31+C30 -> 14174.206 | D31: =C31+D30 -> 16953.192 | E31: =D31+E30 -> 19625.205 | F31: =E31+F30 -> 22942.129 | G31: =F31+G30 -> 25965.402 | H31: =G31+H30 -> 28633.352 | I31: =H31+I30 -> 31715.143 | J31: =I31+J30 -> 34738.416 | ... M31: =L31+M30 -> 43881.746
A32: Cuota del préstamo | B32: =IF(13<=Inversion!$B$49,Inversion!$B$50,0) -> 897.81095 | C32: =IF(14<=Inversion!$B$49,Inversion!$B$50,0) -> 897.81095 | D32: =IF(15<=Inversion!$B$49,Inversion!$B$50,0) -> 897.81095 | E32: =IF(16<=Inversion!$B$49,Inversion!$B$50,0) -> 897.81095 | F32: =IF(17<=Inversion!$B$49,Inversion!$B$50,0) -> 897.81095 | G32: =IF(18<=Inversion!$B$49,Inversion!$B$50,0) -> 897.81095 | H32: =IF(19<=Inversion!$B$49,Inversion!$B$50,0) -> 897.81095 | I32: =IF(20<=Inversion!$B$49,Inversion!$B$50,0) -> 897.81095 | J32: =IF(21<=Inversion!$B$49,Inversion!$B$50,0) -> 897.81095 | K32: =IF(22<=Inversion!$B$49,Inversion!$B$50,0) -> 897.81095 | L32: =IF(23<=Inversion!$B$49,Inversion!$B$50,0) -> 897.81095 | M32: =IF(24<=Inversion!$B$49,Inversion!$B$50,0) -> 897.81095 | N32: =SUM(B32:M32) -> 10773.731
A33: Depreciación (no sale de caja) | B33: =Supuestos!$B$74 -> 134.38889 | C33: =Supuestos!$B$74 -> 134.38889 | D33: =Supuestos!$B$74 -> 134.38889 | E33: =Supuestos!$B$74 -> 134.38889 | F33: =Supuestos!$B$74 -> 134.38889 | G33: =Supuestos!$B$74 -> 134.38889 | H33: =Supuestos!$B$74 -> 134.38889 | I33: =Supuestos!$B$74 -> 134.38889 | ... M33: =Supuestos!$B$74 -> 134.38889 | N33: =SUM(B33:M33) -> 1612.6667
A34: Caja al cierre del mes | B34: =Mensual!M44+B30+B33-B32 -> 12413.584 | C34: =B34+C30+C33-C32 -> 11610.616 | D34: =C34+D30+D33-D32 -> 13626.18 | E34: =D34+E30+E33-E32 -> 15534.771 | F34: =E34+F30+F33-F32 -> 18088.273 | G34: =F34+G30+G33-G32 -> 20348.124 | H34: =G34+H30+H33-H32 -> 22252.652 | I34: =H34+I30+I33-I32 -> 24571.021 | J34: =I34+J30+J33-J32 -> 26830.872 | ... M34: =L34+M30+M33-M32 -> 33683.936
A36: De resultado operativo a utilidad neta (año 2)
A37: Resultado operativo | B37: =N30 -> 30458.668
A38: Más: pagos a cuenta de renta ya restados en el costo de canal (1 % de las ventas sin IGV) | B38: =Supuestos!B28*N23 -> 2731.6
A39: Menos: intereses del préstamo en el año 2 | B39: =-CUMIPMT((1+Inversion!B48)^(1/12)-1,Inversion!B49,Inversion!B47,13,24,0) -> 1582.2421
A40: Utilidad antes de impuestos | B40: =B37+B38-B39 -> 31608.026
A41: Impuesto a la renta del Régimen MYPE Tributario (10 % hasta 15 UIT de utilidad) | B41: =MAX(0,0.1*B40) -> 3160.8026
A42: Utilidad neta del año 2 | B42: =B40-B41 -> 28447.223
